[{"serviceId":"efs","region":"us-west-2","attributes":{"feature":"Atoupm"},"pricePerUnit":"0.1600000000","unit":"USD per unit"},{"serviceId":"efs","region":"us-west-2","attributes":{"feature":"Stmohybph"},"pricePerUnit":"0.0300000000","unit":"USD per unit"},{"serviceId":"efs","region":"us-west-2","attributes":{"feature":"Tlpa"},"pricePerUnit":"6.0000000000","unit":"USD per unit"},{"serviceId":"efs","region":"us-west-2","attributes":{"feature":"Gjdh"},"pricePerUnit":"0.0600000000","unit":"USD per unit"},{"serviceId":"efs","region":"us-west-2","attributes":{"usageType":"Storage","feature":"Infrequent"},"pricePerUnit":"0.0250000000","unit":"USD per GB"},{"serviceId":"efs","region":"us-west-2","attributes":{"usageType":"Request","feature":"Storage"},"pricePerUnit":"0.0300000000","unit":"USD per GB"},{"serviceId":"efs","region":"us-west-2","attributes":{"usageType":"Storage"},"pricePerUnit":"0.1600000000","unit":"USD per GB"},{"serviceId":"efs","region":"us-west-2","attributes":{"usageType":"Storage","feature":"Archive"},"pricePerUnit":"0.0300000000","unit":"USD per GB"},{"serviceId":"efs","region":"us-west-2","attributes":{"feature":"Throughput"},"pricePerUnit":"0.0000000000","unit":"USD per unit"},{"serviceId":"efs","region":"us-west-2","attributes":{"feature":"Throughput"},"pricePerUnit":"6.0000000000","unit":"USD per unit"},{"serviceId":"efs","region":"us-west-2","attributes":{"usageType":"Request","feature":"Infrequent"},"pricePerUnit":"0.0100000000","unit":"USD per GB"},{"serviceId":"efs","region":"us-west-2","attributes":{"usageType":"Storage"},"pricePerUnit":"0.0133000000","unit":"USD per GB"},{"serviceId":"efs","region":"us-west-2","attributes":{"usageType":"Request","feature":"Storage"},"pricePerUnit":"0.0600000000","unit":"USD per GB"},{"serviceId":"efs","region":"us-west-2","attributes":{"usageType":"Storage","feature":"Archive"},"pricePerUnit":"0.0080000000","unit":"USD per GB"},{"serviceId":"efs","region":"us-west-2","attributes":{"usageType":"Storage","feature":"General"},"pricePerUnit":"0.3000000000","unit":"USD per GB"},{"serviceId":"efs","region":"us-west-2","attributes":{"usageType":"Storage","feature":"Infrequent"},"pricePerUnit":"0.0160000000","unit":"USD per GB"},{"serviceId":"efs","region":"us-west-2","attributes":{"usageType":"Storage","feature":"Archive"},"pricePerUnit":"0.0300000000","unit":"USD per GB"},{"serviceId":"efs","region":"us-west-2","attributes":{"usageType":"Request","feature":"Infrequent"},"pricePerUnit":"0.0100000000","unit":"USD per GB"},{"serviceId":"efs","region":"us-west-1","attributes":{"feature":"Atoupm"},"pricePerUnit":"0.1760000000","unit":"USD per unit"},{"serviceId":"efs","region":"us-west-1","attributes":{"feature":"Stmohybph"},"pricePerUnit":"0.0330000000","unit":"USD per unit"},{"serviceId":"efs","region":"us-west-1","attributes":{"feature":"Tlpa"},"pricePerUnit":"6.6000000000","unit":"USD per unit"},{"serviceId":"efs","region":"us-west-1","attributes":{"feature":"Gjdh"},"pricePerUnit":"0.0700000000","unit":"USD per unit"},{"serviceId":"efs","region":"us-west-1","attributes":{"usageType":"Storage","feature":"Infrequent"},"pricePerUnit":"0.0283000000","unit":"USD per GB"},{"serviceId":"efs","region":"us-west-1","attributes":{"usageType":"Request","feature":"Storage"},"pricePerUnit":"0.0300000000","unit":"USD per GB"},{"serviceId":"efs","region":"us-west-1","attributes":{"usageType":"Storage"},"pricePerUnit":"0.1760000000","unit":"USD per GB"},{"serviceId":"efs","region":"us-west-1","attributes":{"usageType":"Storage","feature":"Archive"},"pricePerUnit":"0.0330000000","unit":"USD per GB"},{"serviceId":"efs","region":"us-west-1","attributes":{"feature":"Throughput"},"pricePerUnit":"0.0000000000","unit":"USD per unit"},{"serviceId":"efs","region":"us-west-1","attributes":{"feature":"Throughput"},"pricePerUnit":"6.6000000000","unit":"USD per unit"},{"serviceId":"efs","region":"us-west-1","attributes":{"usageType":"Request","feature":"Infrequent"},"pricePerUnit":"0.0110000000","unit":"USD per GB"},{"serviceId":"efs","region":"us-west-1","attributes":{"usageType":"Storage"},"pricePerUnit":"0.0151000000","unit":"USD per GB"},{"serviceId":"efs","region":"us-west-1","attributes":{"usageType":"Request","feature":"Storage"},"pricePerUnit":"0.0700000000","unit":"USD per GB"},{"serviceId":"efs","region":"us-west-1","attributes":{"usageType":"Storage","feature":"Archive"},"pricePerUnit":"0.0100000000","unit":"USD per GB"},{"serviceId":"efs","region":"us-west-1","attributes":{"usageType":"Storage","feature":"General"},"pricePerUnit":"0.3300000000","unit":"USD per GB"},{"serviceId":"efs","region":"us-west-1","attributes":{"usageType":"Storage","feature":"Infrequent"},"pricePerUnit":"0.0200000000","unit":"USD per GB"},{"serviceId":"efs","region":"us-west-1","attributes":{"usageType":"Storage","feature":"Archive"},"pricePerUnit":"0.0330000000","unit":"USD per GB"},{"serviceId":"efs","region":"us-west-1","attributes":{"usageType":"Request","feature":"Infrequent"},"pricePerUnit":"0.0110000000","unit":"USD per GB"},{"serviceId":"efs","region":"us-east-2","attributes":{"feature":"Atoupm"},"pricePerUnit":"0.1600000000","unit":"USD per unit"},{"serviceId":"efs","region":"us-east-2","attributes":{"feature":"Stmohybph"},"pricePerUnit":"0.0300000000","unit":"USD per unit"},{"serviceId":"efs","region":"us-east-2","attributes":{"feature":"Tlpa"},"pricePerUnit":"6.0000000000","unit":"USD per unit"},{"serviceId":"efs","region":"us-east-2","attributes":{"feature":"Gjdh"},"pricePerUnit":"0.0600000000","unit":"USD per unit"},{"serviceId":"efs","region":"us-east-2","attributes":{"usageType":"Storage","feature":"Infrequent"},"pricePerUnit":"0.0250000000","unit":"USD per GB"},{"serviceId":"efs","region":"us-east-2","attributes":{"usageType":"Request","feature":"Storage"},"pricePerUnit":"0.0300000000","unit":"USD per GB"},{"serviceId":"efs","region":"us-east-2","attributes":{"usageType":"Storage"},"pricePerUnit":"0.1600000000","unit":"USD per GB"},{"serviceId":"efs","region":"us-east-2","attributes":{"usageType":"Storage","feature":"Archive"},"pricePerUnit":"0.0300000000","unit":"USD per GB"},{"serviceId":"efs","region":"us-east-2","attributes":{"feature":"Throughput"},"pricePerUnit":"0.0000000000","unit":"USD per unit"},{"serviceId":"efs","region":"us-east-2","attributes":{"feature":"Throughput"},"pricePerUnit":"6.0000000000","unit":"USD per unit"},{"serviceId":"efs","region":"us-east-2","attributes":{"usageType":"Request","feature":"Infrequent"},"pricePerUnit":"0.0100000000","unit":"USD per GB"},{"serviceId":"efs","region":"us-east-2","attributes":{"usageType":"Storage"},"pricePerUnit":"0.0133000000","unit":"USD per GB"},{"serviceId":"efs","region":"us-east-2","attributes":{"usageType":"Request","feature":"Storage"},"pricePerUnit":"0.0600000000","unit":"USD per GB"},{"serviceId":"efs","region":"us-east-2","attributes":{"usageType":"Storage","feature":"Archive"},"pricePerUnit":"0.0080000000","unit":"USD per GB"},{"serviceId":"efs","region":"us-east-2","attributes":{"usageType":"Storage","feature":"General"},"pricePerUnit":"0.3000000000","unit":"USD per GB"},{"serviceId":"efs","region":"us-east-2","attributes":{"usageType":"Storage","feature":"Infrequent"},"pricePerUnit":"0.0160000000","unit":"USD per GB"},{"serviceId":"efs","region":"us-east-2","attributes":{"usageType":"Storage","feature":"Archive"},"pricePerUnit":"0.0300000000","unit":"USD per GB"},{"serviceId":"efs","region":"us-east-2","attributes":{"usageType":"Request","feature":"Infrequent"},"pricePerUnit":"0.0100000000","unit":"USD per GB"},{"serviceId":"efs","region":"us-east-1","attributes":{"feature":"Atoupm"},"pricePerUnit":"0.1600000000","unit":"USD per unit"},{"serviceId":"efs","region":"us-east-1","attributes":{"feature":"Stmohybph"},"pricePerUnit":"0.0300000000","unit":"USD per unit"},{"serviceId":"efs","region":"us-east-1","attributes":{"feature":"Tlpa"},"pricePerUnit":"6.0000000000","unit":"USD per unit"},{"serviceId":"efs","region":"us-east-1","attributes":{"feature":"Gjdh"},"pricePerUnit":"0.0600000000","unit":"USD per unit"},{"serviceId":"efs","region":"us-east-1","attributes":{"usageType":"Storage","feature":"Infrequent"},"pricePerUnit":"0.0250000000","unit":"USD per GB"},{"serviceId":"efs","region":"us-east-1","attributes":{"usageType":"Request","feature":"Storage"},"pricePerUnit":"0.0300000000","unit":"USD per GB"},{"serviceId":"efs","region":"us-east-1","attributes":{"usageType":"Storage"},"pricePerUnit":"0.1600000000","unit":"USD per GB"},{"serviceId":"efs","region":"us-east-1","attributes":{"usageType":"Storage","feature":"Archive"},"pricePerUnit":"0.0300000000","unit":"USD per GB"},{"serviceId":"efs","region":"us-east-1","attributes":{"feature":"Throughput"},"pricePerUnit":"0.0000000000","unit":"USD per unit"},{"serviceId":"efs","region":"us-east-1","attributes":{"feature":"Throughput"},"pricePerUnit":"6.0000000000","unit":"USD per unit"},{"serviceId":"efs","region":"us-east-1","attributes":{"usageType":"Request","feature":"Infrequent"},"pricePerUnit":"0.0100000000","unit":"USD per GB"},{"serviceId":"efs","region":"us-east-1","attributes":{"usageType":"Storage"},"pricePerUnit":"0.0133000000","unit":"USD per GB"},{"serviceId":"efs","region":"us-east-1","attributes":{"usageType":"Request","feature":"Storage"},"pricePerUnit":"0.0600000000","unit":"USD per GB"},{"serviceId":"efs","region":"us-east-1","attributes":{"usageType":"Storage","feature":"Archive"},"pricePerUnit":"0.0080000000","unit":"USD per GB"},{"serviceId":"efs","region":"us-east-1","attributes":{"usageType":"Storage","feature":"General"},"pricePerUnit":"0.3000000000","unit":"USD per GB"},{"serviceId":"efs","region":"us-east-1","attributes":{"usageType":"Storage","feature":"Infrequent"},"pricePerUnit":"0.0160000000","unit":"USD per GB"},{"serviceId":"efs","region":"us-east-1","attributes":{"usageType":"Storage","feature":"Archive"},"pricePerUnit":"0.0300000000","unit":"USD per GB"},{"serviceId":"efs","region":"us-east-1","attributes":{"usageType":"Request","feature":"Infrequent"},"pricePerUnit":"0.0100000000","unit":"USD per GB"},{"serviceId":"efs","region":"south-america-(sao-paulo)","attributes":{"feature":"Atoupm"},"pricePerUnit":"0.3040000000","unit":"USD per unit"},{"serviceId":"efs","region":"south-america-(sao-paulo)","attributes":{"feature":"Stmohybph"},"pricePerUnit":"0.0570000000","unit":"USD per unit"},{"serviceId":"efs","region":"south-america-(sao-paulo)","attributes":{"feature":"Tlpa"},"pricePerUnit":"11.4000000000","unit":"USD per unit"},{"serviceId":"efs","region":"south-america-(sao-paulo)","attributes":{"feature":"Gjdh"},"pricePerUnit":"0.1100000000","unit":"USD per unit"},{"serviceId":"efs","region":"south-america-(sao-paulo)","attributes":{"usageType":"Storage","feature":"Infrequent"},"pricePerUnit":"0.0440000000","unit":"USD per GB"},{"serviceId":"efs","region":"south-america-(sao-paulo)","attributes":{"usageType":"Request","feature":"Storage"},"pricePerUnit":"0.0600000000","unit":"USD per GB"},{"serviceId":"efs","region":"south-america-(sao-paulo)","attributes":{"usageType":"Storage"},"pricePerUnit":"0.3040000000","unit":"USD per GB"},{"serviceId":"efs","region":"south-america-(sao-paulo)","attributes":{"usageType":"Storage","feature":"Archive"},"pricePerUnit":"0.0570000000","unit":"USD per GB"},{"serviceId":"efs","region":"south-america-(sao-paulo)","attributes":{"feature":"Throughput"},"pricePerUnit":"0.0000000000","unit":"USD per unit"},{"serviceId":"efs","region":"south-america-(sao-paulo)","attributes":{"feature":"Throughput"},"pricePerUnit":"11.4000000000","unit":"USD per unit"},{"serviceId":"efs","region":"south-america-(sao-paulo)","attributes":{"usageType":"Request","feature":"Infrequent"},"pricePerUnit":"0.0190000000","unit":"USD per GB"},{"serviceId":"efs","region":"south-america-(sao-paulo)","attributes":{"usageType":"Storage"},"pricePerUnit":"0.0235000000","unit":"USD per GB"},{"serviceId":"efs","region":"south-america-(sao-paulo)","attributes":{"usageType":"Request","feature":"Storage"},"pricePerUnit":"0.1100000000","unit":"USD per GB"},{"serviceId":"efs","region":"south-america-(sao-paulo)","attributes":{"usageType":"Storage","feature":"Archive"},"pricePerUnit":"0.0166000000","unit":"USD per GB"},{"serviceId":"efs","region":"south-america-(sao-paulo)","attributes":{"usageType":"Storage","feature":"General"},"pricePerUnit":"0.5700000000","unit":"USD per GB"},{"serviceId":"efs","region":"south-america-(sao-paulo)","attributes":{"usageType":"Storage","feature":"Infrequent"},"pricePerUnit":"0.0332000000","unit":"USD per GB"},{"serviceId":"efs","region":"south-america-(sao-paulo)","attributes":{"usageType":"Storage","feature":"Archive"},"pricePerUnit":"0.0570000000","unit":"USD per GB"},{"serviceId":"efs","region":"south-america-(sao-paulo)","attributes":{"usageType":"Request","feature":"Infrequent"},"pricePerUnit":"0.0190000000","unit":"USD per GB"},{"serviceId":"efs","region":"middle-east-(uae)","attributes":{"feature":"Stmohybph"},"pricePerUnit":"0.0360000000","unit":"USD per unit"},{"serviceId":"efs","region":"middle-east-(uae)","attributes":{"feature":"Tlpa"},"pricePerUnit":"7.2000000000","unit":"USD per unit"},{"serviceId":"efs","region":"middle-east-(uae)","attributes":{"feature":"Gjdh"},"pricePerUnit":"0.0700000000","unit":"USD per unit"},{"serviceId":"efs","region":"middle-east-(uae)","attributes":{"usageType":"Storage","feature":"Infrequent"},"pricePerUnit":"0.0270000000","unit":"USD per GB"},{"serviceId":"efs","region":"middle-east-(uae)","attributes":{"usageType":"Request","feature":"Storage"},"pricePerUnit":"0.0400000000","unit":"USD per GB"},{"serviceId":"efs","region":"middle-east-(uae)","attributes":{"usageType":"Storage","feature":"Archive"},"pricePerUnit":"0.0360000000","unit":"USD per GB"},{"serviceId":"efs","region":"middle-east-(uae)","attributes":{"feature":"Throughput"},"pricePerUnit":"0.0000000000","unit":"USD per unit"},{"serviceId":"efs","region":"middle-east-(uae)","attributes":{"feature":"Throughput"},"pricePerUnit":"7.2000000000","unit":"USD per unit"},{"serviceId":"efs","region":"middle-east-(uae)","attributes":{"usageType":"Request","feature":"Infrequent"},"pricePerUnit":"0.0120000000","unit":"USD per GB"},{"serviceId":"efs","region":"middle-east-(uae)","attributes":{"usageType":"Request","feature":"Storage"},"pricePerUnit":"0.0700000000","unit":"USD per GB"},{"serviceId":"efs","region":"middle-east-(uae)","attributes":{"usageType":"Storage","feature":"Archive"},"pricePerUnit":"0.0100000000","unit":"USD per GB"},{"serviceId":"efs","region":"middle-east-(uae)","attributes":{"usageType":"Storage","feature":"General"},"pricePerUnit":"0.3600000000","unit":"USD per GB"},{"serviceId":"efs","region":"middle-east-(uae)","attributes":{"usageType":"Storage","feature":"Infrequent"},"pricePerUnit":"0.0200000000","unit":"USD per GB"},{"serviceId":"efs","region":"middle-east-(uae)","attributes":{"usageType":"Storage","feature":"Archive"},"pricePerUnit":"0.0360000000","unit":"USD per GB"},{"serviceId":"efs","region":"middle-east-(uae)","attributes":{"usageType":"Request","feature":"Infrequent"},"pricePerUnit":"0.0120000000","unit":"USD per GB"},{"serviceId":"efs","region":"middle-east-(bahrain)","attributes":{"feature":"Atoupm"},"pricePerUnit":"0.1920000000","unit":"USD per unit"},{"serviceId":"efs","region":"middle-east-(bahrain)","attributes":{"feature":"Stmohybph"},"pricePerUnit":"0.0360000000","unit":"USD per unit"},{"serviceId":"efs","region":"middle-east-(bahrain)","attributes":{"feature":"Tlpa"},"pricePerUnit":"7.2000000000","unit":"USD per unit"},{"serviceId":"efs","region":"middle-east-(bahrain)","attributes":{"feature":"Gjdh"},"pricePerUnit":"0.0700000000","unit":"USD per unit"},{"serviceId":"efs","region":"middle-east-(bahrain)","attributes":{"usageType":"Storage","feature":"Infrequent"},"pricePerUnit":"0.0270000000","unit":"USD per GB"},{"serviceId":"efs","region":"middle-east-(bahrain)","attributes":{"usageType":"Request","feature":"Storage"},"pricePerUnit":"0.0400000000","unit":"USD per GB"},{"serviceId":"efs","region":"middle-east-(bahrain)","attributes":{"usageType":"Storage"},"pricePerUnit":"0.1920000000","unit":"USD per GB"},{"serviceId":"efs","region":"middle-east-(bahrain)","attributes":{"usageType":"Storage","feature":"Archive"},"pricePerUnit":"0.0360000000","unit":"USD per GB"},{"serviceId":"efs","region":"middle-east-(bahrain)","attributes":{"feature":"Throughput"},"pricePerUnit":"0.0000000000","unit":"USD per unit"},{"serviceId":"efs","region":"middle-east-(bahrain)","attributes":{"feature":"Throughput"},"pricePerUnit":"7.2000000000","unit":"USD per unit"},{"serviceId":"efs","region":"middle-east-(bahrain)","attributes":{"usageType":"Request","feature":"Infrequent"},"pricePerUnit":"0.0120000000","unit":"USD per GB"},{"serviceId":"efs","region":"middle-east-(bahrain)","attributes":{"usageType":"Storage"},"pricePerUnit":"0.0144000000","unit":"USD per GB"},{"serviceId":"efs","region":"middle-east-(bahrain)","attributes":{"usageType":"Request","feature":"Storage"},"pricePerUnit":"0.0700000000","unit":"USD per GB"},{"serviceId":"efs","region":"middle-east-(bahrain)","attributes":{"usageType":"Storage","feature":"Archive"},"pricePerUnit":"0.0100000000","unit":"USD per GB"},{"serviceId":"efs","region":"middle-east-(bahrain)","attributes":{"usageType":"Storage","feature":"General"},"pricePerUnit":"0.3600000000","unit":"USD per GB"},{"serviceId":"efs","region":"middle-east-(bahrain)","attributes":{"usageType":"Storage","feature":"Infrequent"},"pricePerUnit":"0.0200000000","unit":"USD per GB"},{"serviceId":"efs","region":"middle-east-(bahrain)","attributes":{"usageType":"Storage","feature":"Archive"},"pricePerUnit":"0.0360000000","unit":"USD per GB"},{"serviceId":"efs","region":"middle-east-(bahrain)","attributes":{"usageType":"Request","feature":"Infrequent"},"pricePerUnit":"0.0120000000","unit":"USD per GB"},{"serviceId":"efs","region":"mexico-(central)","attributes":{"feature":"Stmohybph"},"pricePerUnit":"0.0315000000","unit":"USD per unit"},{"serviceId":"efs","region":"mexico-(central)","attributes":{"feature":"Tlpa"},"pricePerUnit":"6.3000000000","unit":"USD per unit"},{"serviceId":"efs","region":"mexico-(central)","attributes":{"feature":"Gjdh"},"pricePerUnit":"0.0630000000","unit":"USD per unit"},{"serviceId":"efs","region":"mexico-(central)","attributes":{"usageType":"Storage","feature":"Infrequent"},"pricePerUnit":"0.0262500000","unit":"USD per GB"},{"serviceId":"efs","region":"mexico-(central)","attributes":{"usageType":"Request","feature":"Storage"},"pricePerUnit":"0.0315000000","unit":"USD per GB"},{"serviceId":"efs","region":"mexico-(central)","attributes":{"usageType":"Storage","feature":"Archive"},"pricePerUnit":"0.0315000000","unit":"USD per GB"},{"serviceId":"efs","region":"mexico-(central)","attributes":{"feature":"Throughput"},"pricePerUnit":"0.0000000000","unit":"USD per unit"},{"serviceId":"efs","region":"mexico-(central)","attributes":{"feature":"Throughput"},"pricePerUnit":"6.3000000000","unit":"USD per unit"},{"serviceId":"efs","region":"mexico-(central)","attributes":{"usageType":"Request","feature":"Infrequent"},"pricePerUnit":"0.0105000000","unit":"USD per GB"},{"serviceId":"efs","region":"mexico-(central)","attributes":{"usageType":"Request","feature":"Storage"},"pricePerUnit":"0.0630000000","unit":"USD per GB"},{"serviceId":"efs","region":"mexico-(central)","attributes":{"usageType":"Storage","feature":"Archive"},"pricePerUnit":"0.0084000000","unit":"USD per GB"},{"serviceId":"efs","region":"mexico-(central)","attributes":{"usageType":"Storage","feature":"General"},"pricePerUnit":"0.3150000000","unit":"USD per GB"},{"serviceId":"efs","region":"mexico-(central)","attributes":{"usageType":"Storage","feature":"Infrequent"},"pricePerUnit":"0.0168000000","unit":"USD per GB"},{"serviceId":"efs","region":"mexico-(central)","attributes":{"usageType":"Storage","feature":"Archive"},"pricePerUnit":"0.0315000000","unit":"USD per GB"},{"serviceId":"efs","region":"mexico-(central)","attributes":{"usageType":"Request","feature":"Infrequent"},"pricePerUnit":"0.0105000000","unit":"USD per GB"},{"serviceId":"efs","region":"israel-(tel-aviv)","attributes":{"feature":"Stmohybph"},"pricePerUnit":"0.0396000000","unit":"USD per unit"},{"serviceId":"efs","region":"israel-(tel-aviv)","attributes":{"feature":"Tlpa"},"pricePerUnit":"8.0000000000","unit":"USD per unit"},{"serviceId":"efs","region":"israel-(tel-aviv)","attributes":{"feature":"Gjdh"},"pricePerUnit":"0.0792000000","unit":"USD per unit"},{"serviceId":"efs","region":"israel-(tel-aviv)","attributes":{"usageType":"Storage","feature":"Infrequent"},"pricePerUnit":"0.0272000000","unit":"USD per GB"},{"serviceId":"efs","region":"israel-(tel-aviv)","attributes":{"usageType":"Request","feature":"Storage"},"pricePerUnit":"0.0396000000","unit":"USD per GB"},{"serviceId":"efs","region":"israel-(tel-aviv)","attributes":{"usageType":"Storage","feature":"Archive"},"pricePerUnit":"0.0396000000","unit":"USD per GB"},{"serviceId":"efs","region":"israel-(tel-aviv)","attributes":{"feature":"Throughput"},"pricePerUnit":"0.0000000000","unit":"USD per unit"},{"serviceId":"efs","region":"israel-(tel-aviv)","attributes":{"feature":"Throughput"},"pricePerUnit":"8.0000000000","unit":"USD per unit"},{"serviceId":"efs","region":"israel-(tel-aviv)","attributes":{"usageType":"Request","feature":"Infrequent"},"pricePerUnit":"0.0132000000","unit":"USD per GB"},{"serviceId":"efs","region":"israel-(tel-aviv)","attributes":{"usageType":"Request","feature":"Storage"},"pricePerUnit":"0.0792000000","unit":"USD per GB"},{"serviceId":"efs","region":"israel-(tel-aviv)","attributes":{"usageType":"Storage","feature":"Archive"},"pricePerUnit":"0.0100000000","unit":"USD per GB"},{"serviceId":"efs","region":"israel-(tel-aviv)","attributes":{"usageType":"Storage","feature":"General"},"pricePerUnit":"0.4000000000","unit":"USD per GB"},{"serviceId":"efs","region":"israel-(tel-aviv)","attributes":{"usageType":"Storage","feature":"Infrequent"},"pricePerUnit":"0.0200000000","unit":"USD per GB"},{"serviceId":"efs","region":"israel-(tel-aviv)","attributes":{"usageType":"Storage","feature":"Archive"},"pricePerUnit":"0.0396000000","unit":"USD per GB"},{"serviceId":"efs","region":"israel-(tel-aviv)","attributes":{"usageType":"Request","feature":"Infrequent"},"pricePerUnit":"0.0132000000","unit":"USD per GB"},{"serviceId":"efs","region":"eu-(zurich)","attributes":{"feature":"Stmohybph"},"pricePerUnit":"0.0420000000","unit":"USD per unit"},{"serviceId":"efs","region":"eu-(zurich)","attributes":{"feature":"Tlpa"},"pricePerUnit":"8.5800000000","unit":"USD per unit"},{"serviceId":"efs","region":"eu-(zurich)","attributes":{"feature":"Gjdh"},"pricePerUnit":"0.0700000000","unit":"USD per unit"},{"serviceId":"efs","region":"eu-(zurich)","attributes":{"usageType":"Storage","feature":"Infrequent"},"pricePerUnit":"0.0295000000","unit":"USD per GB"},{"serviceId":"efs","region":"eu-(zurich)","attributes":{"usageType":"Request","feature":"Storage"},"pricePerUnit":"0.0400000000","unit":"USD per GB"},{"serviceId":"efs","region":"eu-(zurich)","attributes":{"usageType":"Storage","feature":"Archive"},"pricePerUnit":"0.0420000000","unit":"USD per GB"},{"serviceId":"efs","region":"eu-(zurich)","attributes":{"feature":"Throughput"},"pricePerUnit":"0.0000000000","unit":"USD per unit"},{"serviceId":"efs","region":"eu-(zurich)","attributes":{"feature":"Throughput"},"pricePerUnit":"8.5800000000","unit":"USD per unit"},{"serviceId":"efs","region":"eu-(zurich)","attributes":{"usageType":"Request","feature":"Infrequent"},"pricePerUnit":"0.0140000000","unit":"USD per GB"},{"serviceId":"efs","region":"eu-(zurich)","attributes":{"usageType":"Request","feature":"Storage"},"pricePerUnit":"0.0700000000","unit":"USD per GB"},{"serviceId":"efs","region":"eu-(zurich)","attributes":{"usageType":"Storage","feature":"Archive"},"pricePerUnit":"0.0110000000","unit":"USD per GB"},{"serviceId":"efs","region":"eu-(zurich)","attributes":{"usageType":"Storage","feature":"General"},"pricePerUnit":"0.4300000000","unit":"USD per GB"},{"serviceId":"efs","region":"eu-(zurich)","attributes":{"usageType":"Storage","feature":"Infrequent"},"pricePerUnit":"0.0220000000","unit":"USD per GB"},{"serviceId":"efs","region":"eu-(zurich)","attributes":{"usageType":"Storage","feature":"Archive"},"pricePerUnit":"0.0420000000","unit":"USD per GB"},{"serviceId":"efs","region":"eu-(zurich)","attributes":{"usageType":"Request","feature":"Infrequent"},"pricePerUnit":"0.0140000000","unit":"USD per GB"},{"serviceId":"efs","region":"eu-(stockholm)","attributes":{"feature":"Atoupm"},"pricePerUnit":"0.1600000000","unit":"USD per unit"},{"serviceId":"efs","region":"eu-(stockholm)","attributes":{"feature":"Stmohybph"},"pricePerUnit":"0.0300000000","unit":"USD per unit"},{"serviceId":"efs","region":"eu-(stockholm)","attributes":{"feature":"Tlpa"},"pricePerUnit":"6.0000000000","unit":"USD per unit"},{"serviceId":"efs","region":"eu-(stockholm)","attributes":{"feature":"Gjdh"},"pricePerUnit":"0.0600000000","unit":"USD per unit"},{"serviceId":"efs","region":"eu-(stockholm)","attributes":{"usageType":"Storage","feature":"Infrequent"},"pricePerUnit":"0.0250000000","unit":"USD per GB"},{"serviceId":"efs","region":"eu-(stockholm)","attributes":{"usageType":"Request","feature":"Storage"},"pricePerUnit":"0.0300000000","unit":"USD per GB"},{"serviceId":"efs","region":"eu-(stockholm)","attributes":{"usageType":"Storage"},"pricePerUnit":"0.1600000000","unit":"USD per GB"},{"serviceId":"efs","region":"eu-(stockholm)","attributes":{"usageType":"Storage","feature":"Archive"},"pricePerUnit":"0.0300000000","unit":"USD per GB"},{"serviceId":"efs","region":"eu-(stockholm)","attributes":{"feature":"Throughput"},"pricePerUnit":"0.0000000000","unit":"USD per unit"},{"serviceId":"efs","region":"eu-(stockholm)","attributes":{"feature":"Throughput"},"pricePerUnit":"6.0000000000","unit":"USD per unit"},{"serviceId":"efs","region":"eu-(stockholm)","attributes":{"usageType":"Request","feature":"Infrequent"},"pricePerUnit":"0.0100000000","unit":"USD per GB"},{"serviceId":"efs","region":"eu-(stockholm)","attributes":{"usageType":"Storage"},"pricePerUnit":"0.0133000000","unit":"USD per GB"},{"serviceId":"efs","region":"eu-(stockholm)","attributes":{"usageType":"Request","feature":"Storage"},"pricePerUnit":"0.0600000000","unit":"USD per GB"},{"serviceId":"efs","region":"eu-(stockholm)","attributes":{"usageType":"Storage","feature":"Archive"},"pricePerUnit":"0.0080000000","unit":"USD per GB"},{"serviceId":"efs","region":"eu-(stockholm)","attributes":{"usageType":"Storage","feature":"General"},"pricePerUnit":"0.3000000000","unit":"USD per GB"},{"serviceId":"efs","region":"eu-(stockholm)","attributes":{"usageType":"Storage","feature":"Infrequent"},"pricePerUnit":"0.0160000000","unit":"USD per GB"},{"serviceId":"efs","region":"eu-(stockholm)","attributes":{"usageType":"Storage","feature":"Archive"},"pricePerUnit":"0.0300000000","unit":"USD per GB"},{"serviceId":"efs","region":"eu-(stockholm)","attributes":{"usageType":"Request","feature":"Infrequent"},"pricePerUnit":"0.0100000000","unit":"USD per GB"},{"serviceId":"efs","region":"eu-(spain)","attributes":{"feature":"Stmohybph"},"pricePerUnit":"0.0330000000","unit":"USD per unit"},{"serviceId":"efs","region":"eu-(spain)","attributes":{"feature":"Tlpa"},"pricePerUnit":"6.6000000000","unit":"USD per unit"},{"serviceId":"efs","region":"eu-(spain)","attributes":{"feature":"Gjdh"},"pricePerUnit":"0.0700000000","unit":"USD per unit"},{"serviceId":"efs","region":"eu-(spain)","attributes":{"usageType":"Storage","feature":"Infrequent"},"pricePerUnit":"0.0250000000","unit":"USD per GB"},{"serviceId":"efs","region":"eu-(spain)","attributes":{"usageType":"Request","feature":"Storage"},"pricePerUnit":"0.0300000000","unit":"USD per GB"},{"serviceId":"efs","region":"eu-(spain)","attributes":{"usageType":"Storage","feature":"Archive"},"pricePerUnit":"0.0330000000","unit":"USD per GB"},{"serviceId":"efs","region":"eu-(spain)","attributes":{"feature":"Throughput"},"pricePerUnit":"0.0000000000","unit":"USD per unit"},{"serviceId":"efs","region":"eu-(spain)","attributes":{"feature":"Throughput"},"pricePerUnit":"6.6000000000","unit":"USD per unit"},{"serviceId":"efs","region":"eu-(spain)","attributes":{"usageType":"Request","feature":"Infrequent"},"pricePerUnit":"0.0110000000","unit":"USD per GB"},{"serviceId":"efs","region":"eu-(spain)","attributes":{"usageType":"Request","feature":"Storage"},"pricePerUnit":"0.0700000000","unit":"USD per GB"},{"serviceId":"efs","region":"eu-(spain)","attributes":{"usageType":"Storage","feature":"Archive"},"pricePerUnit":"0.0100000000","unit":"USD per GB"},{"serviceId":"efs","region":"eu-(spain)","attributes":{"usageType":"Storage","feature":"General"},"pricePerUnit":"0.3300000000","unit":"USD per GB"},{"serviceId":"efs","region":"eu-(spain)","attributes":{"usageType":"Storage","feature":"Infrequent"},"pricePerUnit":"0.0200000000","unit":"USD per GB"},{"serviceId":"efs","region":"eu-(spain)","attributes":{"usageType":"Storage","feature":"Archive"},"pricePerUnit":"0.0330000000","unit":"USD per GB"},{"serviceId":"efs","region":"eu-(spain)","attributes":{"usageType":"Request","feature":"Infrequent"},"pricePerUnit":"0.0110000000","unit":"USD per GB"},{"serviceId":"efs","region":"eu-(paris)","attributes":{"feature":"Atoupm"},"pricePerUnit":"0.1760000000","unit":"USD per unit"},{"serviceId":"efs","region":"eu-(paris)","attributes":{"feature":"Stmohybph"},"pricePerUnit":"0.0330000000","unit":"USD per unit"},{"serviceId":"efs","region":"eu-(paris)","attributes":{"feature":"Tlpa"},"pricePerUnit":"6.6000000000","unit":"USD per unit"},{"serviceId":"efs","region":"eu-(paris)","attributes":{"feature":"Gjdh"},"pricePerUnit":"0.0700000000","unit":"USD per unit"},{"serviceId":"efs","region":"eu-(paris)","attributes":{"usageType":"Storage","feature":"Infrequent"},"pricePerUnit":"0.0261000000","unit":"USD per GB"},{"serviceId":"efs","region":"eu-(paris)","attributes":{"usageType":"Request","feature":"Storage"},"pricePerUnit":"0.0300000000","unit":"USD per GB"},{"serviceId":"efs","region":"eu-(paris)","attributes":{"usageType":"Storage"},"pricePerUnit":"0.1760000000","unit":"USD per GB"},{"serviceId":"efs","region":"eu-(paris)","attributes":{"usageType":"Storage","feature":"Archive"},"pricePerUnit":"0.0330000000","unit":"USD per GB"},{"serviceId":"efs","region":"eu-(paris)","attributes":{"feature":"Throughput"},"pricePerUnit":"0.0000000000","unit":"USD per unit"},{"serviceId":"efs","region":"eu-(paris)","attributes":{"feature":"Throughput"},"pricePerUnit":"6.6000000000","unit":"USD per unit"},{"serviceId":"efs","region":"eu-(paris)","attributes":{"usageType":"Request","feature":"Infrequent"},"pricePerUnit":"0.0110000000","unit":"USD per GB"},{"serviceId":"efs","region":"eu-(paris)","attributes":{"usageType":"Storage"},"pricePerUnit":"0.0139000000","unit":"USD per GB"},{"serviceId":"efs","region":"eu-(paris)","attributes":{"usageType":"Request","feature":"Storage"},"pricePerUnit":"0.0700000000","unit":"USD per GB"},{"serviceId":"efs","region":"eu-(paris)","attributes":{"usageType":"Storage","feature":"Archive"},"pricePerUnit":"0.0100000000","unit":"USD per GB"},{"serviceId":"efs","region":"eu-(paris)","attributes":{"usageType":"Storage","feature":"General"},"pricePerUnit":"0.3300000000","unit":"USD per GB"},{"serviceId":"efs","region":"eu-(paris)","attributes":{"usageType":"Storage","feature":"Infrequent"},"pricePerUnit":"0.0200000000","unit":"USD per GB"},{"serviceId":"efs","region":"eu-(paris)","attributes":{"usageType":"Storage","feature":"Archive"},"pricePerUnit":"0.0330000000","unit":"USD per GB"},{"serviceId":"efs","region":"eu-(paris)","attributes":{"usageType":"Request","feature":"Infrequent"},"pricePerUnit":"0.0110000000","unit":"USD per GB"},{"serviceId":"efs","region":"eu-(milan)","attributes":{"feature":"Atoupm"},"pricePerUnit":"0.1920000000","unit":"USD per unit"},{"serviceId":"efs","region":"eu-(milan)","attributes":{"feature":"Stmohybph"},"pricePerUnit":"0.0360000000","unit":"USD per unit"},{"serviceId":"efs","region":"eu-(milan)","attributes":{"feature":"Tlpa"},"pricePerUnit":"7.2000000000","unit":"USD per unit"},{"serviceId":"efs","region":"eu-(milan)","attributes":{"feature":"Gjdh"},"pricePerUnit":"0.0700000000","unit":"USD per unit"},{"serviceId":"efs","region":"eu-(milan)","attributes":{"usageType":"Storage","feature":"Infrequent"},"pricePerUnit":"0.0260000000","unit":"USD per GB"},{"serviceId":"efs","region":"eu-(milan)","attributes":{"usageType":"Request","feature":"Storage"},"pricePerUnit":"0.0400000000","unit":"USD per GB"},{"serviceId":"efs","region":"eu-(milan)","attributes":{"usageType":"Storage"},"pricePerUnit":"0.1920000000","unit":"USD per GB"},{"serviceId":"efs","region":"eu-(milan)","attributes":{"usageType":"Storage","feature":"Archive"},"pricePerUnit":"0.0360000000","unit":"USD per GB"},{"serviceId":"efs","region":"eu-(milan)","attributes":{"feature":"Throughput"},"pricePerUnit":"0.0000000000","unit":"USD per unit"},{"serviceId":"efs","region":"eu-(milan)","attributes":{"feature":"Throughput"},"pricePerUnit":"7.2000000000","unit":"USD per unit"},{"serviceId":"efs","region":"eu-(milan)","attributes":{"usageType":"Request","feature":"Infrequent"},"pricePerUnit":"0.0120000000","unit":"USD per GB"},{"serviceId":"efs","region":"eu-(milan)","attributes":{"usageType":"Storage"},"pricePerUnit":"0.0139000000","unit":"USD per GB"},{"serviceId":"efs","region":"eu-(milan)","attributes":{"usageType":"Request","feature":"Storage"},"pricePerUnit":"0.0700000000","unit":"USD per GB"},{"serviceId":"efs","region":"eu-(milan)","attributes":{"usageType":"Storage","feature":"Archive"},"pricePerUnit":"0.0100000000","unit":"USD per GB"},{"serviceId":"efs","region":"eu-(milan)","attributes":{"usageType":"Storage","feature":"General"},"pricePerUnit":"0.3600000000","unit":"USD per GB"},{"serviceId":"efs","region":"eu-(milan)","attributes":{"usageType":"Storage","feature":"Infrequent"},"pricePerUnit":"0.0200000000","unit":"USD per GB"},{"serviceId":"efs","region":"eu-(milan)","attributes":{"usageType":"Storage","feature":"Archive"},"pricePerUnit":"0.0360000000","unit":"USD per GB"},{"serviceId":"efs","region":"eu-(milan)","attributes":{"usageType":"Request","feature":"Infrequent"},"pricePerUnit":"0.0120000000","unit":"USD per GB"},{"serviceId":"efs","region":"eu-west-2","attributes":{"feature":"Atoupm"},"pricePerUnit":"0.1760000000","unit":"USD per unit"},{"serviceId":"efs","region":"eu-west-2","attributes":{"feature":"Stmohybph"},"pricePerUnit":"0.0330000000","unit":"USD per unit"},{"serviceId":"efs","region":"eu-west-2","attributes":{"feature":"Tlpa"},"pricePerUnit":"6.6000000000","unit":"USD per unit"},{"serviceId":"efs","region":"eu-west-2","attributes":{"feature":"Gjdh"},"pricePerUnit":"0.0700000000","unit":"USD per unit"},{"serviceId":"efs","region":"eu-west-2","attributes":{"usageType":"Storage","feature":"Infrequent"},"pricePerUnit":"0.0261000000","unit":"USD per GB"},{"serviceId":"efs","region":"eu-west-2","attributes":{"usageType":"Request","feature":"Storage"},"pricePerUnit":"0.0300000000","unit":"USD per GB"},{"serviceId":"efs","region":"eu-west-2","attributes":{"usageType":"Storage"},"pricePerUnit":"0.1760000000","unit":"USD per GB"},{"serviceId":"efs","region":"eu-west-2","attributes":{"usageType":"Storage","feature":"Archive"},"pricePerUnit":"0.0330000000","unit":"USD per GB"},{"serviceId":"efs","region":"eu-west-2","attributes":{"feature":"Throughput"},"pricePerUnit":"0.0000000000","unit":"USD per unit"},{"serviceId":"efs","region":"eu-west-2","attributes":{"feature":"Throughput"},"pricePerUnit":"6.6000000000","unit":"USD per unit"},{"serviceId":"efs","region":"eu-west-2","attributes":{"usageType":"Request","feature":"Infrequent"},"pricePerUnit":"0.0110000000","unit":"USD per GB"},{"serviceId":"efs","region":"eu-west-2","attributes":{"usageType":"Storage"},"pricePerUnit":"0.0139000000","unit":"USD per GB"},{"serviceId":"efs","region":"eu-west-2","attributes":{"usageType":"Request","feature":"Storage"},"pricePerUnit":"0.0700000000","unit":"USD per GB"},{"serviceId":"efs","region":"eu-west-2","attributes":{"usageType":"Storage","feature":"Archive"},"pricePerUnit":"0.0100000000","unit":"USD per GB"},{"serviceId":"efs","region":"eu-west-2","attributes":{"usageType":"Storage","feature":"General"},"pricePerUnit":"0.3300000000","unit":"USD per GB"},{"serviceId":"efs","region":"eu-west-2","attributes":{"usageType":"Storage","feature":"Infrequent"},"pricePerUnit":"0.0200000000","unit":"USD per GB"},{"serviceId":"efs","region":"eu-west-2","attributes":{"usageType":"Storage","feature":"Archive"},"pricePerUnit":"0.0330000000","unit":"USD per GB"},{"serviceId":"efs","region":"eu-west-2","attributes":{"usageType":"Request","feature":"Infrequent"},"pricePerUnit":"0.0110000000","unit":"USD per GB"},{"serviceId":"efs","region":"eu-west-1","attributes":{"feature":"Atoupm"},"pricePerUnit":"0.1760000000","unit":"USD per unit"},{"serviceId":"efs","region":"eu-west-1","attributes":{"feature":"Stmohybph"},"pricePerUnit":"0.0330000000","unit":"USD per unit"},{"serviceId":"efs","region":"eu-west-1","attributes":{"feature":"Tlpa"},"pricePerUnit":"6.6000000000","unit":"USD per unit"},{"serviceId":"efs","region":"eu-west-1","attributes":{"feature":"Gjdh"},"pricePerUnit":"0.0700000000","unit":"USD per unit"},{"serviceId":"efs","region":"eu-west-1","attributes":{"usageType":"Storage","feature":"Infrequent"},"pricePerUnit":"0.0250000000","unit":"USD per GB"},{"serviceId":"efs","region":"eu-west-1","attributes":{"usageType":"Request","feature":"Storage"},"pricePerUnit":"0.0300000000","unit":"USD per GB"},{"serviceId":"efs","region":"eu-west-1","attributes":{"usageType":"Storage"},"pricePerUnit":"0.1760000000","unit":"USD per GB"},{"serviceId":"efs","region":"eu-west-1","attributes":{"usageType":"Storage","feature":"Archive"},"pricePerUnit":"0.0330000000","unit":"USD per GB"},{"serviceId":"efs","region":"eu-west-1","attributes":{"feature":"Throughput"},"pricePerUnit":"0.0000000000","unit":"USD per unit"},{"serviceId":"efs","region":"eu-west-1","attributes":{"feature":"Throughput"},"pricePerUnit":"6.6000000000","unit":"USD per unit"},{"serviceId":"efs","region":"eu-west-1","attributes":{"usageType":"Request","feature":"Infrequent"},"pricePerUnit":"0.0110000000","unit":"USD per GB"},{"serviceId":"efs","region":"eu-west-1","attributes":{"usageType":"Storage"},"pricePerUnit":"0.0133000000","unit":"USD per GB"},{"serviceId":"efs","region":"eu-west-1","attributes":{"usageType":"Request","feature":"Storage"},"pricePerUnit":"0.0700000000","unit":"USD per GB"},{"serviceId":"efs","region":"eu-west-1","attributes":{"usageType":"Storage","feature":"Archive"},"pricePerUnit":"0.0080000000","unit":"USD per GB"},{"serviceId":"efs","region":"eu-west-1","attributes":{"usageType":"Storage","feature":"General"},"pricePerUnit":"0.3300000000","unit":"USD per GB"},{"serviceId":"efs","region":"eu-west-1","attributes":{"usageType":"Storage","feature":"Infrequent"},"pricePerUnit":"0.0160000000","unit":"USD per GB"},{"serviceId":"efs","region":"eu-west-1","attributes":{"usageType":"Storage","feature":"Archive"},"pricePerUnit":"0.0330000000","unit":"USD per GB"},{"serviceId":"efs","region":"eu-west-1","attributes":{"usageType":"Request","feature":"Infrequent"},"pricePerUnit":"0.0110000000","unit":"USD per GB"},{"serviceId":"efs","region":"eu-central-1","attributes":{"feature":"Atoupm"},"pricePerUnit":"0.1920000000","unit":"USD per unit"},{"serviceId":"efs","region":"eu-central-1","attributes":{"feature":"Stmohybph"},"pricePerUnit":"0.0360000000","unit":"USD per unit"},{"serviceId":"efs","region":"eu-central-1","attributes":{"feature":"Tlpa"},"pricePerUnit":"7.2000000000","unit":"USD per unit"},{"serviceId":"efs","region":"eu-central-1","attributes":{"feature":"Gjdh"},"pricePerUnit":"0.0700000000","unit":"USD per unit"},{"serviceId":"efs","region":"eu-central-1","attributes":{"usageType":"Storage","feature":"Infrequent"},"pricePerUnit":"0.0266000000","unit":"USD per GB"},{"serviceId":"efs","region":"eu-central-1","attributes":{"usageType":"Request","feature":"Storage"},"pricePerUnit":"0.0400000000","unit":"USD per GB"},{"serviceId":"efs","region":"eu-central-1","attributes":{"usageType":"Storage"},"pricePerUnit":"0.1920000000","unit":"USD per GB"},{"serviceId":"efs","region":"eu-central-1","attributes":{"usageType":"Storage","feature":"Archive"},"pricePerUnit":"0.0360000000","unit":"USD per GB"},{"serviceId":"efs","region":"eu-central-1","attributes":{"feature":"Throughput"},"pricePerUnit":"0.0000000000","unit":"USD per unit"},{"serviceId":"efs","region":"eu-central-1","attributes":{"feature":"Throughput"},"pricePerUnit":"7.2000000000","unit":"USD per unit"},{"serviceId":"efs","region":"eu-central-1","attributes":{"usageType":"Request","feature":"Infrequent"},"pricePerUnit":"0.0120000000","unit":"USD per GB"},{"serviceId":"efs","region":"eu-central-1","attributes":{"usageType":"Storage"},"pricePerUnit":"0.0142000000","unit":"USD per GB"},{"serviceId":"efs","region":"eu-central-1","attributes":{"usageType":"Request","feature":"Storage"},"pricePerUnit":"0.0700000000","unit":"USD per GB"},{"serviceId":"efs","region":"eu-central-1","attributes":{"usageType":"Storage","feature":"Archive"},"pricePerUnit":"0.0100000000","unit":"USD per GB"},{"serviceId":"efs","region":"eu-central-1","attributes":{"usageType":"Storage","feature":"General"},"pricePerUnit":"0.3600000000","unit":"USD per GB"},{"serviceId":"efs","region":"eu-central-1","attributes":{"usageType":"Storage","feature":"Infrequent"},"pricePerUnit":"0.0200000000","unit":"USD per GB"},{"serviceId":"efs","region":"eu-central-1","attributes":{"usageType":"Storage","feature":"Archive"},"pricePerUnit":"0.0360000000","unit":"USD per GB"},{"serviceId":"efs","region":"eu-central-1","attributes":{"usageType":"Request","feature":"Infrequent"},"pricePerUnit":"0.0120000000","unit":"USD per GB"},{"serviceId":"efs","region":"canada-west-(calgary)","attributes":{"feature":"Atoupm"},"pricePerUnit":"0.1760000000","unit":"USD per unit"},{"serviceId":"efs","region":"canada-west-(calgary)","attributes":{"feature":"Stmohybph"},"pricePerUnit":"0.0330000000","unit":"USD per unit"},{"serviceId":"efs","region":"canada-west-(calgary)","attributes":{"feature":"Tlpa"},"pricePerUnit":"6.6000000000","unit":"USD per unit"},{"serviceId":"efs","region":"canada-west-(calgary)","attributes":{"feature":"Gjdh"},"pricePerUnit":"0.0700000000","unit":"USD per unit"},{"serviceId":"efs","region":"canada-west-(calgary)","attributes":{"usageType":"Storage","feature":"Infrequent"},"pricePerUnit":"0.0272000000","unit":"USD per GB"},{"serviceId":"efs","region":"canada-west-(calgary)","attributes":{"usageType":"Request","feature":"Storage"},"pricePerUnit":"0.0300000000","unit":"USD per GB"},{"serviceId":"efs","region":"canada-west-(calgary)","attributes":{"usageType":"Storage"},"pricePerUnit":"0.1760000000","unit":"USD per GB"},{"serviceId":"efs","region":"canada-west-(calgary)","attributes":{"usageType":"Storage","feature":"Archive"},"pricePerUnit":"0.0330000000","unit":"USD per GB"},{"serviceId":"efs","region":"canada-west-(calgary)","attributes":{"feature":"Throughput"},"pricePerUnit":"0.0000000000","unit":"USD per unit"},{"serviceId":"efs","region":"canada-west-(calgary)","attributes":{"feature":"Throughput"},"pricePerUnit":"6.6000000000","unit":"USD per unit"},{"serviceId":"efs","region":"canada-west-(calgary)","attributes":{"usageType":"Request","feature":"Infrequent"},"pricePerUnit":"0.0110000000","unit":"USD per GB"},{"serviceId":"efs","region":"canada-west-(calgary)","attributes":{"usageType":"Storage"},"pricePerUnit":"0.0145000000","unit":"USD per GB"},{"serviceId":"efs","region":"canada-west-(calgary)","attributes":{"usageType":"Request","feature":"Storage"},"pricePerUnit":"0.0700000000","unit":"USD per GB"},{"serviceId":"efs","region":"canada-west-(calgary)","attributes":{"usageType":"Storage","feature":"Archive"},"pricePerUnit":"0.0100000000","unit":"USD per GB"},{"serviceId":"efs","region":"canada-west-(calgary)","attributes":{"usageType":"Storage","feature":"General"},"pricePerUnit":"0.3300000000","unit":"USD per GB"},{"serviceId":"efs","region":"canada-west-(calgary)","attributes":{"usageType":"Storage","feature":"Infrequent"},"pricePerUnit":"0.0200000000","unit":"USD per GB"},{"serviceId":"efs","region":"canada-west-(calgary)","attributes":{"usageType":"Storage","feature":"Archive"},"pricePerUnit":"0.0330000000","unit":"USD per GB"},{"serviceId":"efs","region":"canada-west-(calgary)","attributes":{"usageType":"Request","feature":"Infrequent"},"pricePerUnit":"0.0110000000","unit":"USD per GB"},{"serviceId":"efs","region":"canada-(central)","attributes":{"feature":"Atoupm"},"pricePerUnit":"0.1760000000","unit":"USD per unit"},{"serviceId":"efs","region":"canada-(central)","attributes":{"feature":"Stmohybph"},"pricePerUnit":"0.0330000000","unit":"USD per unit"},{"serviceId":"efs","region":"canada-(central)","attributes":{"feature":"Tlpa"},"pricePerUnit":"6.6000000000","unit":"USD per unit"},{"serviceId":"efs","region":"canada-(central)","attributes":{"feature":"Gjdh"},"pricePerUnit":"0.0700000000","unit":"USD per unit"},{"serviceId":"efs","region":"canada-(central)","attributes":{"usageType":"Storage","feature":"Infrequent"},"pricePerUnit":"0.0272000000","unit":"USD per GB"},{"serviceId":"efs","region":"canada-(central)","attributes":{"usageType":"Request","feature":"Storage"},"pricePerUnit":"0.0300000000","unit":"USD per GB"},{"serviceId":"efs","region":"canada-(central)","attributes":{"usageType":"Storage"},"pricePerUnit":"0.1760000000","unit":"USD per GB"},{"serviceId":"efs","region":"canada-(central)","attributes":{"usageType":"Storage","feature":"Archive"},"pricePerUnit":"0.0330000000","unit":"USD per GB"},{"serviceId":"efs","region":"canada-(central)","attributes":{"feature":"Throughput"},"pricePerUnit":"0.0000000000","unit":"USD per unit"},{"serviceId":"efs","region":"canada-(central)","attributes":{"feature":"Throughput"},"pricePerUnit":"6.6000000000","unit":"USD per unit"},{"serviceId":"efs","region":"canada-(central)","attributes":{"usageType":"Request","feature":"Infrequent"},"pricePerUnit":"0.0110000000","unit":"USD per GB"},{"serviceId":"efs","region":"canada-(central)","attributes":{"usageType":"Storage"},"pricePerUnit":"0.0145000000","unit":"USD per GB"},{"serviceId":"efs","region":"canada-(central)","attributes":{"usageType":"Request","feature":"Storage"},"pricePerUnit":"0.0700000000","unit":"USD per GB"},{"serviceId":"efs","region":"canada-(central)","attributes":{"usageType":"Storage","feature":"Archive"},"pricePerUnit":"0.0100000000","unit":"USD per GB"},{"serviceId":"efs","region":"canada-(central)","attributes":{"usageType":"Storage","feature":"General"},"pricePerUnit":"0.3300000000","unit":"USD per GB"},{"serviceId":"efs","region":"canada-(central)","attributes":{"usageType":"Storage","feature":"Infrequent"},"pricePerUnit":"0.0200000000","unit":"USD per GB"},{"serviceId":"efs","region":"canada-(central)","attributes":{"usageType":"Storage","feature":"Archive"},"pricePerUnit":"0.0330000000","unit":"USD per GB"},{"serviceId":"efs","region":"canada-(central)","attributes":{"usageType":"Request","feature":"Infrequent"},"pricePerUnit":"0.0110000000","unit":"USD per GB"},{"serviceId":"efs","region":"ap-northeast-1","attributes":{"feature":"Atoupm"},"pricePerUnit":"0.1920000000","unit":"USD per unit"},{"serviceId":"efs","region":"ap-northeast-1","attributes":{"feature":"Stmohybph"},"pricePerUnit":"0.0360000000","unit":"USD per unit"},{"serviceId":"efs","region":"ap-northeast-1","attributes":{"feature":"Tlpa"},"pricePerUnit":"7.2000000000","unit":"USD per unit"},{"serviceId":"efs","region":"ap-northeast-1","attributes":{"feature":"Gjdh"},"pricePerUnit":"0.0700000000","unit":"USD per unit"},{"serviceId":"efs","region":"ap-northeast-1","attributes":{"usageType":"Storage","feature":"Infrequent"},"pricePerUnit":"0.0272000000","unit":"USD per GB"},{"serviceId":"efs","region":"ap-northeast-1","attributes":{"usageType":"Request","feature":"Storage"},"pricePerUnit":"0.0400000000","unit":"USD per GB"},{"serviceId":"efs","region":"ap-northeast-1","attributes":{"usageType":"Storage"},"pricePerUnit":"0.1920000000","unit":"USD per GB"},{"serviceId":"efs","region":"ap-northeast-1","attributes":{"usageType":"Storage","feature":"Archive"},"pricePerUnit":"0.0360000000","unit":"USD per GB"},{"serviceId":"efs","region":"ap-northeast-1","attributes":{"feature":"Throughput"},"pricePerUnit":"0.0000000000","unit":"USD per unit"},{"serviceId":"efs","region":"ap-northeast-1","attributes":{"feature":"Throughput"},"pricePerUnit":"7.2000000000","unit":"USD per unit"},{"serviceId":"efs","region":"ap-northeast-1","attributes":{"usageType":"Request","feature":"Infrequent"},"pricePerUnit":"0.0120000000","unit":"USD per GB"},{"serviceId":"efs","region":"ap-northeast-1","attributes":{"usageType":"Storage"},"pricePerUnit":"0.0145000000","unit":"USD per GB"},{"serviceId":"efs","region":"ap-northeast-1","attributes":{"usageType":"Request","feature":"Storage"},"pricePerUnit":"0.0700000000","unit":"USD per GB"},{"serviceId":"efs","region":"ap-northeast-1","attributes":{"usageType":"Storage","feature":"Archive"},"pricePerUnit":"0.0100000000","unit":"USD per GB"},{"serviceId":"efs","region":"ap-northeast-1","attributes":{"usageType":"Storage","feature":"General"},"pricePerUnit":"0.3600000000","unit":"USD per GB"},{"serviceId":"efs","region":"ap-northeast-1","attributes":{"usageType":"Storage","feature":"Infrequent"},"pricePerUnit":"0.0200000000","unit":"USD per GB"},{"serviceId":"efs","region":"ap-northeast-1","attributes":{"usageType":"Storage","feature":"Archive"},"pricePerUnit":"0.0360000000","unit":"USD per GB"},{"serviceId":"efs","region":"ap-northeast-1","attributes":{"usageType":"Request","feature":"Infrequent"},"pricePerUnit":"0.0120000000","unit":"USD per GB"},{"serviceId":"efs","region":"asia-pacific-(thailand)","attributes":{"feature":"Stmohybph"},"pricePerUnit":"0.0320000000","unit":"USD per unit"},{"serviceId":"efs","region":"asia-pacific-(thailand)","attributes":{"feature":"Tlpa"},"pricePerUnit":"6.4800000000","unit":"USD per unit"},{"serviceId":"efs","region":"asia-pacific-(thailand)","attributes":{"feature":"Gjdh"},"pricePerUnit":"0.0630000000","unit":"USD per unit"},{"serviceId":"efs","region":"asia-pacific-(thailand)","attributes":{"usageType":"Storage","feature":"Infrequent"},"pricePerUnit":"0.0245000000","unit":"USD per GB"},{"serviceId":"efs","region":"asia-pacific-(thailand)","attributes":{"usageType":"Request","feature":"Storage"},"pricePerUnit":"0.0360000000","unit":"USD per GB"},{"serviceId":"efs","region":"asia-pacific-(thailand)","attributes":{"usageType":"Storage","feature":"Archive"},"pricePerUnit":"0.0320000000","unit":"USD per GB"},{"serviceId":"efs","region":"asia-pacific-(thailand)","attributes":{"feature":"Throughput"},"pricePerUnit":"0.0000000000","unit":"USD per unit"},{"serviceId":"efs","region":"asia-pacific-(thailand)","attributes":{"feature":"Throughput"},"pricePerUnit":"6.4800000000","unit":"USD per unit"},{"serviceId":"efs","region":"asia-pacific-(thailand)","attributes":{"usageType":"Request","feature":"Infrequent"},"pricePerUnit":"0.0110000000","unit":"USD per GB"},{"serviceId":"efs","region":"asia-pacific-(thailand)","attributes":{"usageType":"Request","feature":"Storage"},"pricePerUnit":"0.0630000000","unit":"USD per GB"},{"serviceId":"efs","region":"asia-pacific-(thailand)","attributes":{"usageType":"Storage","feature":"Archive"},"pricePerUnit":"0.0090000000","unit":"USD per GB"},{"serviceId":"efs","region":"asia-pacific-(thailand)","attributes":{"usageType":"Storage","feature":"General"},"pricePerUnit":"0.3240000000","unit":"USD per GB"},{"serviceId":"efs","region":"asia-pacific-(thailand)","attributes":{"usageType":"Storage","feature":"Infrequent"},"pricePerUnit":"0.0180000000","unit":"USD per GB"},{"serviceId":"efs","region":"asia-pacific-(thailand)","attributes":{"usageType":"Storage","feature":"Archive"},"pricePerUnit":"0.0320000000","unit":"USD per GB"},{"serviceId":"efs","region":"asia-pacific-(thailand)","attributes":{"usageType":"Request","feature":"Infrequent"},"pricePerUnit":"0.0110000000","unit":"USD per GB"},{"serviceId":"efs","region":"asia-pacific-(taipei)","attributes":{"feature":"Stmohybph"},"pricePerUnit":"0.0324000000","unit":"USD per unit"},{"serviceId":"efs","region":"asia-pacific-(taipei)","attributes":{"feature":"Tlpa"},"pricePerUnit":"6.8400000000","unit":"USD per unit"},{"serviceId":"efs","region":"asia-pacific-(taipei)","attributes":{"feature":"Gjdh"},"pricePerUnit":"0.0665000000","unit":"USD per unit"},{"serviceId":"efs","region":"asia-pacific-(taipei)","attributes":{"usageType":"Storage","feature":"Infrequent"},"pricePerUnit":"0.0245000000","unit":"USD per GB"},{"serviceId":"efs","region":"asia-pacific-(taipei)","attributes":{"usageType":"Request","feature":"Storage"},"pricePerUnit":"0.0380000000","unit":"USD per GB"},{"serviceId":"efs","region":"asia-pacific-(taipei)","attributes":{"usageType":"Storage","feature":"Archive"},"pricePerUnit":"0.0324000000","unit":"USD per GB"},{"serviceId":"efs","region":"asia-pacific-(taipei)","attributes":{"feature":"Throughput"},"pricePerUnit":"0.0000000000","unit":"USD per unit"},{"serviceId":"efs","region":"asia-pacific-(taipei)","attributes":{"feature":"Throughput"},"pricePerUnit":"6.8400000000","unit":"USD per unit"},{"serviceId":"efs","region":"asia-pacific-(taipei)","attributes":{"usageType":"Request","feature":"Infrequent"},"pricePerUnit":"0.0108000000","unit":"USD per GB"},{"serviceId":"efs","region":"asia-pacific-(taipei)","attributes":{"usageType":"Request","feature":"Storage"},"pricePerUnit":"0.0665000000","unit":"USD per GB"},{"serviceId":"efs","region":"asia-pacific-(taipei)","attributes":{"usageType":"Storage","feature":"Archive"},"pricePerUnit":"0.0100000000","unit":"USD per GB"},{"serviceId":"efs","region":"asia-pacific-(taipei)","attributes":{"usageType":"Storage","feature":"General"},"pricePerUnit":"0.3240000000","unit":"USD per GB"},{"serviceId":"efs","region":"asia-pacific-(taipei)","attributes":{"usageType":"Storage","feature":"Infrequent"},"pricePerUnit":"0.0180000000","unit":"USD per GB"},{"serviceId":"efs","region":"asia-pacific-(taipei)","attributes":{"usageType":"Storage","feature":"Archive"},"pricePerUnit":"0.0324000000","unit":"USD per GB"},{"serviceId":"efs","region":"asia-pacific-(taipei)","attributes":{"usageType":"Request","feature":"Infrequent"},"pricePerUnit":"0.0108000000","unit":"USD per GB"},{"serviceId":"efs","region":"ap-southeast-2","attributes":{"feature":"Atoupm"},"pricePerUnit":"0.1920000000","unit":"USD per unit"},{"serviceId":"efs","region":"ap-southeast-2","attributes":{"feature":"Stmohybph"},"pricePerUnit":"0.0360000000","unit":"USD per unit"},{"serviceId":"efs","region":"ap-southeast-2","attributes":{"feature":"Tlpa"},"pricePerUnit":"7.2000000000","unit":"USD per unit"},{"serviceId":"efs","region":"ap-southeast-2","attributes":{"feature":"Gjdh"},"pricePerUnit":"0.0700000000","unit":"USD per unit"},{"serviceId":"efs","region":"ap-southeast-2","attributes":{"usageType":"Storage","feature":"Infrequent"},"pricePerUnit":"0.0272000000","unit":"USD per GB"},{"serviceId":"efs","region":"ap-southeast-2","attributes":{"usageType":"Request","feature":"Storage"},"pricePerUnit":"0.0400000000","unit":"USD per GB"},{"serviceId":"efs","region":"ap-southeast-2","attributes":{"usageType":"Storage"},"pricePerUnit":"0.1920000000","unit":"USD per GB"},{"serviceId":"efs","region":"ap-southeast-2","attributes":{"usageType":"Storage","feature":"Archive"},"pricePerUnit":"0.0360000000","unit":"USD per GB"},{"serviceId":"efs","region":"ap-southeast-2","attributes":{"feature":"Throughput"},"pricePerUnit":"0.0000000000","unit":"USD per unit"},{"serviceId":"efs","region":"ap-southeast-2","attributes":{"feature":"Throughput"},"pricePerUnit":"7.2000000000","unit":"USD per unit"},{"serviceId":"efs","region":"ap-southeast-2","attributes":{"usageType":"Request","feature":"Infrequent"},"pricePerUnit":"0.0120000000","unit":"USD per GB"},{"serviceId":"efs","region":"ap-southeast-2","attributes":{"usageType":"Storage"},"pricePerUnit":"0.0145000000","unit":"USD per GB"},{"serviceId":"efs","region":"ap-southeast-2","attributes":{"usageType":"Request","feature":"Storage"},"pricePerUnit":"0.0700000000","unit":"USD per GB"},{"serviceId":"efs","region":"ap-southeast-2","attributes":{"usageType":"Storage","feature":"Archive"},"pricePerUnit":"0.0100000000","unit":"USD per GB"},{"serviceId":"efs","region":"ap-southeast-2","attributes":{"usageType":"Storage","feature":"General"},"pricePerUnit":"0.3600000000","unit":"USD per GB"},{"serviceId":"efs","region":"ap-southeast-2","attributes":{"usageType":"Storage","feature":"Infrequent"},"pricePerUnit":"0.0200000000","unit":"USD per GB"},{"serviceId":"efs","region":"ap-southeast-2","attributes":{"usageType":"Storage","feature":"Archive"},"pricePerUnit":"0.0360000000","unit":"USD per GB"},{"serviceId":"efs","region":"ap-southeast-2","attributes":{"usageType":"Request","feature":"Infrequent"},"pricePerUnit":"0.0120000000","unit":"USD per GB"},{"serviceId":"efs","region":"ap-southeast-1","attributes":{"feature":"Atoupm"},"pricePerUnit":"0.1920000000","unit":"USD per unit"},{"serviceId":"efs","region":"ap-southeast-1","attributes":{"feature":"Stmohybph"},"pricePerUnit":"0.0360000000","unit":"USD per unit"},{"serviceId":"efs","region":"ap-southeast-1","attributes":{"feature":"Tlpa"},"pricePerUnit":"7.2000000000","unit":"USD per unit"},{"serviceId":"efs","region":"ap-southeast-1","attributes":{"feature":"Gjdh"},"pricePerUnit":"0.0700000000","unit":"USD per unit"},{"serviceId":"efs","region":"ap-southeast-1","attributes":{"usageType":"Storage","feature":"Infrequent"},"pricePerUnit":"0.0272000000","unit":"USD per GB"},{"serviceId":"efs","region":"ap-southeast-1","attributes":{"usageType":"Request","feature":"Storage"},"pricePerUnit":"0.0400000000","unit":"USD per GB"},{"serviceId":"efs","region":"ap-southeast-1","attributes":{"usageType":"Storage"},"pricePerUnit":"0.1920000000","unit":"USD per GB"},{"serviceId":"efs","region":"ap-southeast-1","attributes":{"usageType":"Storage","feature":"Archive"},"pricePerUnit":"0.0360000000","unit":"USD per GB"},{"serviceId":"efs","region":"ap-southeast-1","attributes":{"feature":"Throughput"},"pricePerUnit":"0.0000000000","unit":"USD per unit"},{"serviceId":"efs","region":"ap-southeast-1","attributes":{"feature":"Throughput"},"pricePerUnit":"7.2000000000","unit":"USD per unit"},{"serviceId":"efs","region":"ap-southeast-1","attributes":{"usageType":"Request","feature":"Infrequent"},"pricePerUnit":"0.0120000000","unit":"USD per GB"},{"serviceId":"efs","region":"ap-southeast-1","attributes":{"usageType":"Storage"},"pricePerUnit":"0.0145000000","unit":"USD per GB"},{"serviceId":"efs","region":"ap-southeast-1","attributes":{"usageType":"Request","feature":"Storage"},"pricePerUnit":"0.0700000000","unit":"USD per GB"},{"serviceId":"efs","region":"ap-southeast-1","attributes":{"usageType":"Storage","feature":"Archive"},"pricePerUnit":"0.0100000000","unit":"USD per GB"},{"serviceId":"efs","region":"ap-southeast-1","attributes":{"usageType":"Storage","feature":"General"},"pricePerUnit":"0.3600000000","unit":"USD per GB"},{"serviceId":"efs","region":"ap-southeast-1","attributes":{"usageType":"Storage","feature":"Infrequent"},"pricePerUnit":"0.0200000000","unit":"USD per GB"},{"serviceId":"efs","region":"ap-southeast-1","attributes":{"usageType":"Storage","feature":"Archive"},"pricePerUnit":"0.0360000000","unit":"USD per GB"},{"serviceId":"efs","region":"ap-southeast-1","attributes":{"usageType":"Request","feature":"Infrequent"},"pricePerUnit":"0.0120000000","unit":"USD per GB"},{"serviceId":"efs","region":"asia-pacific-(seoul)","attributes":{"feature":"Atoupm"},"pricePerUnit":"0.1760000000","unit":"USD per unit"},{"serviceId":"efs","region":"asia-pacific-(seoul)","attributes":{"feature":"Stmohybph"},"pricePerUnit":"0.0330000000","unit":"USD per unit"},{"serviceId":"efs","region":"asia-pacific-(seoul)","attributes":{"feature":"Tlpa"},"pricePerUnit":"6.6000000000","unit":"USD per unit"},{"serviceId":"efs","region":"asia-pacific-(seoul)","attributes":{"feature":"Gjdh"},"pricePerUnit":"0.0700000000","unit":"USD per unit"},{"serviceId":"efs","region":"asia-pacific-(seoul)","attributes":{"usageType":"Storage","feature":"Infrequent"},"pricePerUnit":"0.0272000000","unit":"USD per GB"},{"serviceId":"efs","region":"asia-pacific-(seoul)","attributes":{"usageType":"Request","feature":"Storage"},"pricePerUnit":"0.0300000000","unit":"USD per GB"},{"serviceId":"efs","region":"asia-pacific-(seoul)","attributes":{"usageType":"Storage"},"pricePerUnit":"0.1760000000","unit":"USD per GB"},{"serviceId":"efs","region":"asia-pacific-(seoul)","attributes":{"usageType":"Storage","feature":"Archive"},"pricePerUnit":"0.0330000000","unit":"USD per GB"},{"serviceId":"efs","region":"asia-pacific-(seoul)","attributes":{"feature":"Throughput"},"pricePerUnit":"0.0000000000","unit":"USD per unit"},{"serviceId":"efs","region":"asia-pacific-(seoul)","attributes":{"feature":"Throughput"},"pricePerUnit":"6.6000000000","unit":"USD per unit"},{"serviceId":"efs","region":"asia-pacific-(seoul)","attributes":{"usageType":"Request","feature":"Infrequent"},"pricePerUnit":"0.0110000000","unit":"USD per GB"},{"serviceId":"efs","region":"asia-pacific-(seoul)","attributes":{"usageType":"Storage"},"pricePerUnit":"0.0145000000","unit":"USD per GB"},{"serviceId":"efs","region":"asia-pacific-(seoul)","attributes":{"usageType":"Request","feature":"Storage"},"pricePerUnit":"0.0700000000","unit":"USD per GB"},{"serviceId":"efs","region":"asia-pacific-(seoul)","attributes":{"usageType":"Storage","feature":"Archive"},"pricePerUnit":"0.0100000000","unit":"USD per GB"},{"serviceId":"efs","region":"asia-pacific-(seoul)","attributes":{"usageType":"Storage","feature":"General"},"pricePerUnit":"0.3300000000","unit":"USD per GB"},{"serviceId":"efs","region":"asia-pacific-(seoul)","attributes":{"usageType":"Storage","feature":"Infrequent"},"pricePerUnit":"0.0200000000","unit":"USD per GB"},{"serviceId":"efs","region":"asia-pacific-(seoul)","attributes":{"usageType":"Storage","feature":"Archive"},"pricePerUnit":"0.0330000000","unit":"USD per GB"},{"serviceId":"efs","region":"asia-pacific-(seoul)","attributes":{"usageType":"Request","feature":"Infrequent"},"pricePerUnit":"0.0110000000","unit":"USD per GB"},{"serviceId":"efs","region":"asia-pacific-(osaka)","attributes":{"feature":"Atoupm"},"pricePerUnit":"0.1920000000","unit":"USD per unit"},{"serviceId":"efs","region":"asia-pacific-(osaka)","attributes":{"feature":"Stmohybph"},"pricePerUnit":"0.0360000000","unit":"USD per unit"},{"serviceId":"efs","region":"asia-pacific-(osaka)","attributes":{"feature":"Tlpa"},"pricePerUnit":"7.2000000000","unit":"USD per unit"},{"serviceId":"efs","region":"asia-pacific-(osaka)","attributes":{"feature":"Gjdh"},"pricePerUnit":"0.0700000000","unit":"USD per unit"},{"serviceId":"efs","region":"asia-pacific-(osaka)","attributes":{"usageType":"Storage","feature":"Infrequent"},"pricePerUnit":"0.0272000000","unit":"USD per GB"},{"serviceId":"efs","region":"asia-pacific-(osaka)","attributes":{"usageType":"Request","feature":"Storage"},"pricePerUnit":"0.0400000000","unit":"USD per GB"},{"serviceId":"efs","region":"asia-pacific-(osaka)","attributes":{"usageType":"Storage"},"pricePerUnit":"0.1920000000","unit":"USD per GB"},{"serviceId":"efs","region":"asia-pacific-(osaka)","attributes":{"usageType":"Storage","feature":"Archive"},"pricePerUnit":"0.0360000000","unit":"USD per GB"},{"serviceId":"efs","region":"asia-pacific-(osaka)","attributes":{"feature":"Throughput"},"pricePerUnit":"0.0000000000","unit":"USD per unit"},{"serviceId":"efs","region":"asia-pacific-(osaka)","attributes":{"feature":"Throughput"},"pricePerUnit":"7.2000000000","unit":"USD per unit"},{"serviceId":"efs","region":"asia-pacific-(osaka)","attributes":{"usageType":"Request","feature":"Infrequent"},"pricePerUnit":"0.0120000000","unit":"USD per GB"},{"serviceId":"efs","region":"asia-pacific-(osaka)","attributes":{"usageType":"Storage"},"pricePerUnit":"0.0145000000","unit":"USD per GB"},{"serviceId":"efs","region":"asia-pacific-(osaka)","attributes":{"usageType":"Request","feature":"Storage"},"pricePerUnit":"0.0700000000","unit":"USD per GB"},{"serviceId":"efs","region":"asia-pacific-(osaka)","attributes":{"usageType":"Storage","feature":"Archive"},"pricePerUnit":"0.0100000000","unit":"USD per GB"},{"serviceId":"efs","region":"asia-pacific-(osaka)","attributes":{"usageType":"Storage","feature":"General"},"pricePerUnit":"0.3600000000","unit":"USD per GB"},{"serviceId":"efs","region":"asia-pacific-(osaka)","attributes":{"usageType":"Storage","feature":"Infrequent"},"pricePerUnit":"0.0200000000","unit":"USD per GB"},{"serviceId":"efs","region":"asia-pacific-(osaka)","attributes":{"usageType":"Storage","feature":"Archive"},"pricePerUnit":"0.0360000000","unit":"USD per GB"},{"serviceId":"efs","region":"asia-pacific-(osaka)","attributes":{"usageType":"Request","feature":"Infrequent"},"pricePerUnit":"0.0120000000","unit":"USD per GB"},{"serviceId":"efs","region":"asia-pacific-(new-zealand)","attributes":{"feature":"Stmohybph"},"pricePerUnit":"0.0378000000","unit":"USD per unit"},{"serviceId":"efs","region":"asia-pacific-(new-zealand)","attributes":{"feature":"Tlpa"},"pricePerUnit":"7.5600000000","unit":"USD per unit"},{"serviceId":"efs","region":"asia-pacific-(new-zealand)","attributes":{"feature":"Gjdh"},"pricePerUnit":"0.0735000000","unit":"USD per unit"},{"serviceId":"efs","region":"asia-pacific-(new-zealand)","attributes":{"usageType":"Storage","feature":"Infrequent"},"pricePerUnit":"0.0285600000","unit":"USD per GB"},{"serviceId":"efs","region":"asia-pacific-(new-zealand)","attributes":{"usageType":"Request","feature":"Storage"},"pricePerUnit":"0.0420000000","unit":"USD per GB"},{"serviceId":"efs","region":"asia-pacific-(new-zealand)","attributes":{"usageType":"Storage","feature":"Archive"},"pricePerUnit":"0.0378000000","unit":"USD per GB"},{"serviceId":"efs","region":"asia-pacific-(new-zealand)","attributes":{"feature":"Throughput"},"pricePerUnit":"0.0000000000","unit":"USD per unit"},{"serviceId":"efs","region":"asia-pacific-(new-zealand)","attributes":{"feature":"Throughput"},"pricePerUnit":"7.5600000000","unit":"USD per unit"},{"serviceId":"efs","region":"asia-pacific-(new-zealand)","attributes":{"usageType":"Request","feature":"Infrequent"},"pricePerUnit":"0.0126000000","unit":"USD per GB"},{"serviceId":"efs","region":"asia-pacific-(new-zealand)","attributes":{"usageType":"Request","feature":"Storage"},"pricePerUnit":"0.0735000000","unit":"USD per GB"},{"serviceId":"efs","region":"asia-pacific-(new-zealand)","attributes":{"usageType":"Storage","feature":"Archive"},"pricePerUnit":"0.0105000000","unit":"USD per GB"},{"serviceId":"efs","region":"asia-pacific-(new-zealand)","attributes":{"usageType":"Storage","feature":"General"},"pricePerUnit":"0.3780000000","unit":"USD per GB"},{"serviceId":"efs","region":"asia-pacific-(new-zealand)","attributes":{"usageType":"Storage","feature":"Infrequent"},"pricePerUnit":"0.0210000000","unit":"USD per GB"},{"serviceId":"efs","region":"asia-pacific-(new-zealand)","attributes":{"usageType":"Storage","feature":"Archive"},"pricePerUnit":"0.0378000000","unit":"USD per GB"},{"serviceId":"efs","region":"asia-pacific-(new-zealand)","attributes":{"usageType":"Request","feature":"Infrequent"},"pricePerUnit":"0.0126000000","unit":"USD per GB"},{"serviceId":"efs","region":"asia-pacific-(mumbai)","attributes":{"feature":"Atoupm"},"pricePerUnit":"0.1760000000","unit":"USD per unit"},{"serviceId":"efs","region":"asia-pacific-(mumbai)","attributes":{"feature":"Stmohybph"},"pricePerUnit":"0.0330000000","unit":"USD per unit"},{"serviceId":"efs","region":"asia-pacific-(mumbai)","attributes":{"feature":"Tlpa"},"pricePerUnit":"6.6000000000","unit":"USD per unit"},{"serviceId":"efs","region":"asia-pacific-(mumbai)","attributes":{"feature":"Gjdh"},"pricePerUnit":"0.0700000000","unit":"USD per unit"},{"serviceId":"efs","region":"asia-pacific-(mumbai)","attributes":{"usageType":"Storage","feature":"Infrequent"},"pricePerUnit":"0.0272000000","unit":"USD per GB"},{"serviceId":"efs","region":"asia-pacific-(mumbai)","attributes":{"usageType":"Request","feature":"Storage"},"pricePerUnit":"0.0300000000","unit":"USD per GB"},{"serviceId":"efs","region":"asia-pacific-(mumbai)","attributes":{"usageType":"Storage"},"pricePerUnit":"0.1760000000","unit":"USD per GB"},{"serviceId":"efs","region":"asia-pacific-(mumbai)","attributes":{"usageType":"Storage","feature":"Archive"},"pricePerUnit":"0.0330000000","unit":"USD per GB"},{"serviceId":"efs","region":"asia-pacific-(mumbai)","attributes":{"feature":"Throughput"},"pricePerUnit":"0.0000000000","unit":"USD per unit"},{"serviceId":"efs","region":"asia-pacific-(mumbai)","attributes":{"feature":"Throughput"},"pricePerUnit":"6.6000000000","unit":"USD per unit"},{"serviceId":"efs","region":"asia-pacific-(mumbai)","attributes":{"usageType":"Request","feature":"Infrequent"},"pricePerUnit":"0.0110000000","unit":"USD per GB"},{"serviceId":"efs","region":"asia-pacific-(mumbai)","attributes":{"usageType":"Storage"},"pricePerUnit":"0.0145000000","unit":"USD per GB"},{"serviceId":"efs","region":"asia-pacific-(mumbai)","attributes":{"usageType":"Request","feature":"Storage"},"pricePerUnit":"0.0700000000","unit":"USD per GB"},{"serviceId":"efs","region":"asia-pacific-(mumbai)","attributes":{"usageType":"Storage","feature":"Archive"},"pricePerUnit":"0.0100000000","unit":"USD per GB"},{"serviceId":"efs","region":"asia-pacific-(mumbai)","attributes":{"usageType":"Storage","feature":"General"},"pricePerUnit":"0.3300000000","unit":"USD per GB"},{"serviceId":"efs","region":"asia-pacific-(mumbai)","attributes":{"usageType":"Storage","feature":"Infrequent"},"pricePerUnit":"0.0200000000","unit":"USD per GB"},{"serviceId":"efs","region":"asia-pacific-(mumbai)","attributes":{"usageType":"Storage","feature":"Archive"},"pricePerUnit":"0.0330000000","unit":"USD per GB"},{"serviceId":"efs","region":"asia-pacific-(mumbai)","attributes":{"usageType":"Request","feature":"Infrequent"},"pricePerUnit":"0.0110000000","unit":"USD per GB"},{"serviceId":"efs","region":"asia-pacific-(melbourne)","attributes":{"feature":"Stmohybph"},"pricePerUnit":"0.0360000000","unit":"USD per unit"},{"serviceId":"efs","region":"asia-pacific-(melbourne)","attributes":{"feature":"Tlpa"},"pricePerUnit":"7.2000000000","unit":"USD per unit"},{"serviceId":"efs","region":"asia-pacific-(melbourne)","attributes":{"feature":"Gjdh"},"pricePerUnit":"0.0720000000","unit":"USD per unit"},{"serviceId":"efs","region":"asia-pacific-(melbourne)","attributes":{"usageType":"Storage","feature":"Infrequent"},"pricePerUnit":"0.0272000000","unit":"USD per GB"},{"serviceId":"efs","region":"asia-pacific-(melbourne)","attributes":{"usageType":"Request","feature":"Storage"},"pricePerUnit":"0.0360000000","unit":"USD per GB"},{"serviceId":"efs","region":"asia-pacific-(melbourne)","attributes":{"usageType":"Storage","feature":"Archive"},"pricePerUnit":"0.0360000000","unit":"USD per GB"},{"serviceId":"efs","region":"asia-pacific-(melbourne)","attributes":{"feature":"Throughput"},"pricePerUnit":"0.0000000000","unit":"USD per unit"},{"serviceId":"efs","region":"asia-pacific-(melbourne)","attributes":{"feature":"Throughput"},"pricePerUnit":"7.2000000000","unit":"USD per unit"},{"serviceId":"efs","region":"asia-pacific-(melbourne)","attributes":{"usageType":"Request","feature":"Infrequent"},"pricePerUnit":"0.0120000000","unit":"USD per GB"},{"serviceId":"efs","region":"asia-pacific-(melbourne)","attributes":{"usageType":"Request","feature":"Storage"},"pricePerUnit":"0.0720000000","unit":"USD per GB"},{"serviceId":"efs","region":"asia-pacific-(melbourne)","attributes":{"usageType":"Storage","feature":"Archive"},"pricePerUnit":"0.0100000000","unit":"USD per GB"},{"serviceId":"efs","region":"asia-pacific-(melbourne)","attributes":{"usageType":"Storage","feature":"General"},"pricePerUnit":"0.3600000000","unit":"USD per GB"},{"serviceId":"efs","region":"asia-pacific-(melbourne)","attributes":{"usageType":"Storage","feature":"Infrequent"},"pricePerUnit":"0.0200000000","unit":"USD per GB"},{"serviceId":"efs","region":"asia-pacific-(melbourne)","attributes":{"usageType":"Storage","feature":"Archive"},"pricePerUnit":"0.0360000000","unit":"USD per GB"},{"serviceId":"efs","region":"asia-pacific-(melbourne)","attributes":{"usageType":"Request","feature":"Infrequent"},"pricePerUnit":"0.0120000000","unit":"USD per GB"},{"serviceId":"efs","region":"asia-pacific-(malaysia)","attributes":{"feature":"Stmohybph"},"pricePerUnit":"0.0320000000","unit":"USD per unit"},{"serviceId":"efs","region":"asia-pacific-(malaysia)","attributes":{"feature":"Tlpa"},"pricePerUnit":"6.4800000000","unit":"USD per unit"},{"serviceId":"efs","region":"asia-pacific-(malaysia)","attributes":{"feature":"Gjdh"},"pricePerUnit":"0.0630000000","unit":"USD per unit"},{"serviceId":"efs","region":"asia-pacific-(malaysia)","attributes":{"usageType":"Storage","feature":"Infrequent"},"pricePerUnit":"0.0245000000","unit":"USD per GB"},{"serviceId":"efs","region":"asia-pacific-(malaysia)","attributes":{"usageType":"Request","feature":"Storage"},"pricePerUnit":"0.0360000000","unit":"USD per GB"},{"serviceId":"efs","region":"asia-pacific-(malaysia)","attributes":{"usageType":"Storage","feature":"Archive"},"pricePerUnit":"0.0320000000","unit":"USD per GB"},{"serviceId":"efs","region":"asia-pacific-(malaysia)","attributes":{"feature":"Throughput"},"pricePerUnit":"0.0000000000","unit":"USD per unit"},{"serviceId":"efs","region":"asia-pacific-(malaysia)","attributes":{"feature":"Throughput"},"pricePerUnit":"6.4800000000","unit":"USD per unit"},{"serviceId":"efs","region":"asia-pacific-(malaysia)","attributes":{"usageType":"Request","feature":"Infrequent"},"pricePerUnit":"0.0110000000","unit":"USD per GB"},{"serviceId":"efs","region":"asia-pacific-(malaysia)","attributes":{"usageType":"Request","feature":"Storage"},"pricePerUnit":"0.0630000000","unit":"USD per GB"},{"serviceId":"efs","region":"asia-pacific-(malaysia)","attributes":{"usageType":"Storage","feature":"Archive"},"pricePerUnit":"0.0090000000","unit":"USD per GB"},{"serviceId":"efs","region":"asia-pacific-(malaysia)","attributes":{"usageType":"Storage","feature":"General"},"pricePerUnit":"0.3240000000","unit":"USD per GB"},{"serviceId":"efs","region":"asia-pacific-(malaysia)","attributes":{"usageType":"Storage","feature":"Infrequent"},"pricePerUnit":"0.0180000000","unit":"USD per GB"},{"serviceId":"efs","region":"asia-pacific-(malaysia)","attributes":{"usageType":"Storage","feature":"Archive"},"pricePerUnit":"0.0320000000","unit":"USD per GB"},{"serviceId":"efs","region":"asia-pacific-(malaysia)","attributes":{"usageType":"Request","feature":"Infrequent"},"pricePerUnit":"0.0110000000","unit":"USD per GB"},{"serviceId":"efs","region":"asia-pacific-(jakarta)","attributes":{"feature":"Stmohybph"},"pricePerUnit":"0.0360000000","unit":"USD per unit"},{"serviceId":"efs","region":"asia-pacific-(jakarta)","attributes":{"feature":"Tlpa"},"pricePerUnit":"7.2000000000","unit":"USD per unit"},{"serviceId":"efs","region":"asia-pacific-(jakarta)","attributes":{"feature":"Gjdh"},"pricePerUnit":"0.0700000000","unit":"USD per unit"},{"serviceId":"efs","region":"asia-pacific-(jakarta)","attributes":{"usageType":"Storage","feature":"Infrequent"},"pricePerUnit":"0.0272000000","unit":"USD per GB"},{"serviceId":"efs","region":"asia-pacific-(jakarta)","attributes":{"usageType":"Request","feature":"Storage"},"pricePerUnit":"0.0400000000","unit":"USD per GB"},{"serviceId":"efs","region":"asia-pacific-(jakarta)","attributes":{"usageType":"Storage","feature":"Archive"},"pricePerUnit":"0.0360000000","unit":"USD per GB"},{"serviceId":"efs","region":"asia-pacific-(jakarta)","attributes":{"feature":"Throughput"},"pricePerUnit":"0.0000000000","unit":"USD per unit"},{"serviceId":"efs","region":"asia-pacific-(jakarta)","attributes":{"feature":"Throughput"},"pricePerUnit":"7.2000000000","unit":"USD per unit"},{"serviceId":"efs","region":"asia-pacific-(jakarta)","attributes":{"usageType":"Request","feature":"Infrequent"},"pricePerUnit":"0.0120000000","unit":"USD per GB"},{"serviceId":"efs","region":"asia-pacific-(jakarta)","attributes":{"usageType":"Request","feature":"Storage"},"pricePerUnit":"0.0700000000","unit":"USD per GB"},{"serviceId":"efs","region":"asia-pacific-(jakarta)","attributes":{"usageType":"Storage","feature":"Archive"},"pricePerUnit":"0.0100000000","unit":"USD per GB"},{"serviceId":"efs","region":"asia-pacific-(jakarta)","attributes":{"usageType":"Storage","feature":"General"},"pricePerUnit":"0.3600000000","unit":"USD per GB"},{"serviceId":"efs","region":"asia-pacific-(jakarta)","attributes":{"usageType":"Storage","feature":"Infrequent"},"pricePerUnit":"0.0200000000","unit":"USD per GB"},{"serviceId":"efs","region":"asia-pacific-(jakarta)","attributes":{"usageType":"Storage","feature":"Archive"},"pricePerUnit":"0.0360000000","unit":"USD per GB"},{"serviceId":"efs","region":"asia-pacific-(jakarta)","attributes":{"usageType":"Request","feature":"Infrequent"},"pricePerUnit":"0.0120000000","unit":"USD per GB"},{"serviceId":"efs","region":"asia-pacific-(hyderabad)","attributes":{"feature":"Stmohybph"},"pricePerUnit":"0.0330000000","unit":"USD per unit"},{"serviceId":"efs","region":"asia-pacific-(hyderabad)","attributes":{"feature":"Tlpa"},"pricePerUnit":"6.6000000000","unit":"USD per unit"},{"serviceId":"efs","region":"asia-pacific-(hyderabad)","attributes":{"feature":"Gjdh"},"pricePerUnit":"0.0700000000","unit":"USD per unit"},{"serviceId":"efs","region":"asia-pacific-(hyderabad)","attributes":{"usageType":"Storage","feature":"Infrequent"},"pricePerUnit":"0.0272000000","unit":"USD per GB"},{"serviceId":"efs","region":"asia-pacific-(hyderabad)","attributes":{"usageType":"Request","feature":"Storage"},"pricePerUnit":"0.0300000000","unit":"USD per GB"},{"serviceId":"efs","region":"asia-pacific-(hyderabad)","attributes":{"usageType":"Storage","feature":"Archive"},"pricePerUnit":"0.0330000000","unit":"USD per GB"},{"serviceId":"efs","region":"asia-pacific-(hyderabad)","attributes":{"feature":"Throughput"},"pricePerUnit":"0.0000000000","unit":"USD per unit"},{"serviceId":"efs","region":"asia-pacific-(hyderabad)","attributes":{"feature":"Throughput"},"pricePerUnit":"6.6000000000","unit":"USD per unit"},{"serviceId":"efs","region":"asia-pacific-(hyderabad)","attributes":{"usageType":"Request","feature":"Infrequent"},"pricePerUnit":"0.0110000000","unit":"USD per GB"},{"serviceId":"efs","region":"asia-pacific-(hyderabad)","attributes":{"usageType":"Request","feature":"Storage"},"pricePerUnit":"0.0700000000","unit":"USD per GB"},{"serviceId":"efs","region":"asia-pacific-(hyderabad)","attributes":{"usageType":"Storage","feature":"Archive"},"pricePerUnit":"0.0100000000","unit":"USD per GB"},{"serviceId":"efs","region":"asia-pacific-(hyderabad)","attributes":{"usageType":"Storage","feature":"General"},"pricePerUnit":"0.3300000000","unit":"USD per GB"},{"serviceId":"efs","region":"asia-pacific-(hyderabad)","attributes":{"usageType":"Storage","feature":"Infrequent"},"pricePerUnit":"0.0200000000","unit":"USD per GB"},{"serviceId":"efs","region":"asia-pacific-(hyderabad)","attributes":{"usageType":"Storage","feature":"Archive"},"pricePerUnit":"0.0330000000","unit":"USD per GB"},{"serviceId":"efs","region":"asia-pacific-(hyderabad)","attributes":{"usageType":"Request","feature":"Infrequent"},"pricePerUnit":"0.0110000000","unit":"USD per GB"},{"serviceId":"efs","region":"asia-pacific-(hong-kong)","attributes":{"feature":"Atoupm"},"pricePerUnit":"0.2080000000","unit":"USD per unit"},{"serviceId":"efs","region":"asia-pacific-(hong-kong)","attributes":{"feature":"Stmohybph"},"pricePerUnit":"0.0390000000","unit":"USD per unit"},{"serviceId":"efs","region":"asia-pacific-(hong-kong)","attributes":{"feature":"Tlpa"},"pricePerUnit":"7.8000000000","unit":"USD per unit"},{"serviceId":"efs","region":"asia-pacific-(hong-kong)","attributes":{"feature":"Gjdh"},"pricePerUnit":"0.0800000000","unit":"USD per unit"},{"serviceId":"efs","region":"asia-pacific-(hong-kong)","attributes":{"usageType":"Storage","feature":"Infrequent"},"pricePerUnit":"0.0270000000","unit":"USD per GB"},{"serviceId":"efs","region":"asia-pacific-(hong-kong)","attributes":{"usageType":"Request","feature":"Storage"},"pricePerUnit":"0.0400000000","unit":"USD per GB"},{"serviceId":"efs","region":"asia-pacific-(hong-kong)","attributes":{"usageType":"Storage"},"pricePerUnit":"0.2080000000","unit":"USD per GB"},{"serviceId":"efs","region":"asia-pacific-(hong-kong)","attributes":{"usageType":"Storage","feature":"Archive"},"pricePerUnit":"0.0390000000","unit":"USD per GB"},{"serviceId":"efs","region":"asia-pacific-(hong-kong)","attributes":{"feature":"Throughput"},"pricePerUnit":"0.0000000000","unit":"USD per unit"},{"serviceId":"efs","region":"asia-pacific-(hong-kong)","attributes":{"feature":"Throughput"},"pricePerUnit":"7.8000000000","unit":"USD per unit"},{"serviceId":"efs","region":"asia-pacific-(hong-kong)","attributes":{"usageType":"Request","feature":"Infrequent"},"pricePerUnit":"0.0130000000","unit":"USD per GB"},{"serviceId":"efs","region":"asia-pacific-(hong-kong)","attributes":{"usageType":"Storage"},"pricePerUnit":"0.0144000000","unit":"USD per GB"},{"serviceId":"efs","region":"asia-pacific-(hong-kong)","attributes":{"usageType":"Request","feature":"Storage"},"pricePerUnit":"0.0800000000","unit":"USD per GB"},{"serviceId":"efs","region":"asia-pacific-(hong-kong)","attributes":{"usageType":"Storage","feature":"Archive"},"pricePerUnit":"0.0100000000","unit":"USD per GB"},{"serviceId":"efs","region":"asia-pacific-(hong-kong)","attributes":{"usageType":"Storage","feature":"General"},"pricePerUnit":"0.3900000000","unit":"USD per GB"},{"serviceId":"efs","region":"asia-pacific-(hong-kong)","attributes":{"usageType":"Storage","feature":"Infrequent"},"pricePerUnit":"0.0200000000","unit":"USD per GB"},{"serviceId":"efs","region":"asia-pacific-(hong-kong)","attributes":{"usageType":"Storage","feature":"Archive"},"pricePerUnit":"0.0390000000","unit":"USD per GB"},{"serviceId":"efs","region":"asia-pacific-(hong-kong)","attributes":{"usageType":"Request","feature":"Infrequent"},"pricePerUnit":"0.0130000000","unit":"USD per GB"},{"serviceId":"efs","region":"africa-(cape-town)","attributes":{"feature":"Atoupm"},"pricePerUnit":"0.2080000000","unit":"USD per unit"},{"serviceId":"efs","region":"africa-(cape-town)","attributes":{"feature":"Stmohybph"},"pricePerUnit":"0.0390000000","unit":"USD per unit"},{"serviceId":"efs","region":"africa-(cape-town)","attributes":{"feature":"Tlpa"},"pricePerUnit":"7.8000000000","unit":"USD per unit"},{"serviceId":"efs","region":"africa-(cape-town)","attributes":{"feature":"Gjdh"},"pricePerUnit":"0.0800000000","unit":"USD per unit"},{"serviceId":"efs","region":"africa-(cape-town)","attributes":{"usageType":"Storage","feature":"Infrequent"},"pricePerUnit":"0.0300000000","unit":"USD per GB"},{"serviceId":"efs","region":"africa-(cape-town)","attributes":{"usageType":"Request","feature":"Storage"},"pricePerUnit":"0.0400000000","unit":"USD per GB"},{"serviceId":"efs","region":"africa-(cape-town)","attributes":{"usageType":"Storage"},"pricePerUnit":"0.2080000000","unit":"USD per GB"},{"serviceId":"efs","region":"africa-(cape-town)","attributes":{"usageType":"Storage","feature":"Archive"},"pricePerUnit":"0.0390000000","unit":"USD per GB"},{"serviceId":"efs","region":"africa-(cape-town)","attributes":{"feature":"Throughput"},"pricePerUnit":"0.0000000000","unit":"USD per unit"},{"serviceId":"efs","region":"africa-(cape-town)","attributes":{"feature":"Throughput"},"pricePerUnit":"7.8000000000","unit":"USD per unit"},{"serviceId":"efs","region":"africa-(cape-town)","attributes":{"usageType":"Request","feature":"Infrequent"},"pricePerUnit":"0.0130000000","unit":"USD per GB"},{"serviceId":"efs","region":"africa-(cape-town)","attributes":{"usageType":"Storage"},"pricePerUnit":"0.0160000000","unit":"USD per GB"},{"serviceId":"efs","region":"africa-(cape-town)","attributes":{"usageType":"Request","feature":"Storage"},"pricePerUnit":"0.0800000000","unit":"USD per GB"},{"serviceId":"efs","region":"africa-(cape-town)","attributes":{"usageType":"Storage","feature":"Archive"},"pricePerUnit":"0.0100000000","unit":"USD per GB"},{"serviceId":"efs","region":"africa-(cape-town)","attributes":{"usageType":"Storage","feature":"General"},"pricePerUnit":"0.3900000000","unit":"USD per GB"},{"serviceId":"efs","region":"africa-(cape-town)","attributes":{"usageType":"Storage","feature":"Infrequent"},"pricePerUnit":"0.0200000000","unit":"USD per GB"},{"serviceId":"efs","region":"africa-(cape-town)","attributes":{"usageType":"Storage","feature":"Archive"},"pricePerUnit":"0.0390000000","unit":"USD per GB"},{"serviceId":"efs","region":"africa-(cape-town)","attributes":{"usageType":"Request","feature":"Infrequent"},"pricePerUnit":"0.0130000000","unit":"USD per GB"},{"serviceId":"efs","region":"aws-govcloud-(us-east)","attributes":{"feature":"Atoupm"},"pricePerUnit":"0.1920000000","unit":"USD per unit"},{"serviceId":"efs","region":"aws-govcloud-(us-east)","attributes":{"feature":"Stmohybph"},"pricePerUnit":"0.0360000000","unit":"USD per unit"},{"serviceId":"efs","region":"aws-govcloud-(us-east)","attributes":{"feature":"Tlpa"},"pricePerUnit":"7.2000000000","unit":"USD per unit"},{"serviceId":"efs","region":"aws-govcloud-(us-east)","attributes":{"feature":"Gjdh"},"pricePerUnit":"0.0700000000","unit":"USD per unit"},{"serviceId":"efs","region":"aws-govcloud-(us-east)","attributes":{"usageType":"Storage","feature":"Infrequent"},"pricePerUnit":"0.0424000000","unit":"USD per GB"},{"serviceId":"efs","region":"aws-govcloud-(us-east)","attributes":{"usageType":"Request","feature":"Storage"},"pricePerUnit":"0.0400000000","unit":"USD per GB"},{"serviceId":"efs","region":"aws-govcloud-(us-east)","attributes":{"usageType":"Storage"},"pricePerUnit":"0.1920000000","unit":"USD per GB"},{"serviceId":"efs","region":"aws-govcloud-(us-east)","attributes":{"usageType":"Storage","feature":"Archive"},"pricePerUnit":"0.0360000000","unit":"USD per GB"},{"serviceId":"efs","region":"aws-govcloud-(us-east)","attributes":{"feature":"Throughput"},"pricePerUnit":"0.0000000000","unit":"USD per unit"},{"serviceId":"efs","region":"aws-govcloud-(us-east)","attributes":{"feature":"Throughput"},"pricePerUnit":"7.2000000000","unit":"USD per unit"},{"serviceId":"efs","region":"aws-govcloud-(us-east)","attributes":{"usageType":"Request","feature":"Infrequent"},"pricePerUnit":"0.0120000000","unit":"USD per GB"},{"serviceId":"efs","region":"aws-govcloud-(us-east)","attributes":{"usageType":"Storage"},"pricePerUnit":"0.0226000000","unit":"USD per GB"},{"serviceId":"efs","region":"aws-govcloud-(us-east)","attributes":{"usageType":"Request","feature":"Storage"},"pricePerUnit":"0.0700000000","unit":"USD per GB"},{"serviceId":"efs","region":"aws-govcloud-(us-east)","attributes":{"usageType":"Storage","feature":"Archive"},"pricePerUnit":"0.0128000000","unit":"USD per GB"},{"serviceId":"efs","region":"aws-govcloud-(us-east)","attributes":{"usageType":"Storage","feature":"General"},"pricePerUnit":"0.3600000000","unit":"USD per GB"},{"serviceId":"efs","region":"aws-govcloud-(us-east)","attributes":{"usageType":"Storage","feature":"Infrequent"},"pricePerUnit":"0.0256000000","unit":"USD per GB"},{"serviceId":"efs","region":"aws-govcloud-(us-east)","attributes":{"usageType":"Storage","feature":"Archive"},"pricePerUnit":"0.0360000000","unit":"USD per GB"},{"serviceId":"efs","region":"aws-govcloud-(us-east)","attributes":{"usageType":"Request","feature":"Infrequent"},"pricePerUnit":"0.0120000000","unit":"USD per GB"},{"serviceId":"efs","region":"aws-govcloud-(us)","attributes":{"feature":"Atoupm"},"pricePerUnit":"0.1920000000","unit":"USD per unit"},{"serviceId":"efs","region":"aws-govcloud-(us)","attributes":{"feature":"Stmohybph"},"pricePerUnit":"0.0360000000","unit":"USD per unit"},{"serviceId":"efs","region":"aws-govcloud-(us)","attributes":{"feature":"Tlpa"},"pricePerUnit":"7.2000000000","unit":"USD per unit"},{"serviceId":"efs","region":"aws-govcloud-(us)","attributes":{"feature":"Gjdh"},"pricePerUnit":"0.0700000000","unit":"USD per unit"},{"serviceId":"efs","region":"aws-govcloud-(us)","attributes":{"usageType":"Storage","feature":"Infrequent"},"pricePerUnit":"0.0424000000","unit":"USD per GB"},{"serviceId":"efs","region":"aws-govcloud-(us)","attributes":{"usageType":"Request","feature":"Storage"},"pricePerUnit":"0.0400000000","unit":"USD per GB"},{"serviceId":"efs","region":"aws-govcloud-(us)","attributes":{"usageType":"Storage"},"pricePerUnit":"0.1920000000","unit":"USD per GB"},{"serviceId":"efs","region":"aws-govcloud-(us)","attributes":{"usageType":"Storage","feature":"Archive"},"pricePerUnit":"0.0360000000","unit":"USD per GB"},{"serviceId":"efs","region":"aws-govcloud-(us)","attributes":{"feature":"Throughput"},"pricePerUnit":"0.0000000000","unit":"USD per unit"},{"serviceId":"efs","region":"aws-govcloud-(us)","attributes":{"feature":"Throughput"},"pricePerUnit":"7.2000000000","unit":"USD per unit"},{"serviceId":"efs","region":"aws-govcloud-(us)","attributes":{"usageType":"Request","feature":"Infrequent"},"pricePerUnit":"0.0120000000","unit":"USD per GB"},{"serviceId":"efs","region":"aws-govcloud-(us)","attributes":{"usageType":"Storage"},"pricePerUnit":"0.0226000000","unit":"USD per GB"},{"serviceId":"efs","region":"aws-govcloud-(us)","attributes":{"usageType":"Request","feature":"Storage"},"pricePerUnit":"0.0700000000","unit":"USD per GB"},{"serviceId":"efs","region":"aws-govcloud-(us)","attributes":{"usageType":"Storage","feature":"Archive"},"pricePerUnit":"0.0128000000","unit":"USD per GB"},{"serviceId":"efs","region":"aws-govcloud-(us)","attributes":{"usageType":"Storage","feature":"General"},"pricePerUnit":"0.3600000000","unit":"USD per GB"},{"serviceId":"efs","region":"aws-govcloud-(us)","attributes":{"usageType":"Storage","feature":"Infrequent"},"pricePerUnit":"0.0256000000","unit":"USD per GB"},{"serviceId":"efs","region":"aws-govcloud-(us)","attributes":{"usageType":"Storage","feature":"Archive"},"pricePerUnit":"0.0360000000","unit":"USD per GB"},{"serviceId":"efs","region":"aws-govcloud-(us)","attributes":{"usageType":"Request","feature":"Infrequent"},"pricePerUnit":"0.0120000000","unit":"USD per GB"}]