[{"serviceId":"macie","region":"us-west-2","attributes":{"feature":"Xtph"},"pricePerUnit":"0.0000000000","unit":"USD per unit"},{"serviceId":"macie","region":"us-west-2","attributes":{"feature":"Tdym"},"pricePerUnit":"0.0000000000","unit":"USD per unit"},{"serviceId":"macie","region":"us-west-2","attributes":{"feature":"Zvbyf"},"pricePerUnit":"1.0000000000","unit":"USD per unit"},{"serviceId":"macie","region":"us-west-2","attributes":{"feature":"Mjek"},"pricePerUnit":"0.0000000000","unit":"USD per unit"},{"serviceId":"macie","region":"us-west-2","attributes":{"feature":"Pkdjm"},"pricePerUnit":"0.0000040000","unit":"USD per unit"},{"serviceId":"macie","region":"us-west-2","attributes":{"usageType":"Storage","feature":"Extended"},"pricePerUnit":"0.0500000000","unit":"USD per GB"},{"serviceId":"macie","region":"us-west-2","attributes":{"feature":"Tier"},"pricePerUnit":"0.0000000000","unit":"USD per GB"},{"serviceId":"macie","region":"us-west-2","attributes":{"feature":"Content"},"pricePerUnit":"0.0000000000","unit":"USD per GB"},{"serviceId":"macie","region":"us-west-2","attributes":{"feature":"Content"},"pricePerUnit":"0.0000000000","unit":"USD per GB"},{"serviceId":"macie","region":"us-west-2","attributes":{"usageType":"Data Transfer","feature":"Security"},"pricePerUnit":"0.0000000000","unit":"USD per unit"},{"serviceId":"macie","region":"us-west-2","attributes":{"usageType":"Data Transfer","feature":"Security"},"pricePerUnit":"0.0000000000","unit":"USD per unit"},{"serviceId":"macie","region":"us-west-2","attributes":{"feature":"Security"},"pricePerUnit":"0.0000000033","unit":"USD per unit"},{"serviceId":"macie","region":"us-west-2","attributes":{"feature":"Security"},"pricePerUnit":"0.0000000000","unit":"USD per unit"},{"serviceId":"macie","region":"us-west-2","attributes":{"usageType":"Data Transfer","feature":"Security"},"pricePerUnit":"0.0032880000","unit":"USD per unit"},{"serviceId":"macie","region":"us-west-2","attributes":{"usageType":"Data Transfer","feature":"Security"},"pricePerUnit":"0.0032880000","unit":"USD per unit"},{"serviceId":"macie","region":"us-west-2","attributes":{"usageType":"Data Transfer","feature":"Security"},"pricePerUnit":"0.5000000000","unit":"USD per GB"},{"serviceId":"macie","region":"us-west-2","attributes":{"feature":"Security"},"pricePerUnit":"0.0000000000","unit":"USD per unit"},{"serviceId":"macie","region":"us-west-2","attributes":{"usageType":"Data Transfer","feature":"Security"},"pricePerUnit":"0.0000000000","unit":"USD per GB"},{"serviceId":"macie","region":"us-west-2","attributes":{"usageType":"Data Transfer","feature":"Security"},"pricePerUnit":"0.2500000000","unit":"USD per GB"},{"serviceId":"macie","region":"us-west-2","attributes":{"usageType":"Data Transfer","feature":"Security"},"pricePerUnit":"1.0000000000","unit":"USD per GB"},{"serviceId":"macie","region":"us-west-2","attributes":{"usageType":"Data Transfer","feature":"Tier"},"pricePerUnit":"0.0000000000","unit":"USD per GB"},{"serviceId":"macie","region":"us-west-2","attributes":{"feature":"Cloud"},"pricePerUnit":"0.0000040000","unit":"USD per unit"},{"serviceId":"macie","region":"us-west-1","attributes":{"feature":"Xtph"},"pricePerUnit":"0.0000000000","unit":"USD per unit"},{"serviceId":"macie","region":"us-west-1","attributes":{"feature":"Tdym"},"pricePerUnit":"0.0000000000","unit":"USD per unit"},{"serviceId":"macie","region":"us-west-1","attributes":{"feature":"Zvbyf"},"pricePerUnit":"1.5500000000","unit":"USD per unit"},{"serviceId":"macie","region":"us-west-1","attributes":{"feature":"Mjek"},"pricePerUnit":"0.0000000000","unit":"USD per unit"},{"serviceId":"macie","region":"us-west-1","attributes":{"usageType":"Data Transfer","feature":"Security"},"pricePerUnit":"0.0000000000","unit":"USD per unit"},{"serviceId":"macie","region":"us-west-1","attributes":{"usageType":"Data Transfer","feature":"Security"},"pricePerUnit":"0.0000000000","unit":"USD per unit"},{"serviceId":"macie","region":"us-west-1","attributes":{"feature":"Security"},"pricePerUnit":"0.0000000051","unit":"USD per unit"},{"serviceId":"macie","region":"us-west-1","attributes":{"feature":"Security"},"pricePerUnit":"0.0000000000","unit":"USD per unit"},{"serviceId":"macie","region":"us-west-1","attributes":{"usageType":"Data Transfer","feature":"Security"},"pricePerUnit":"0.0032880000","unit":"USD per unit"},{"serviceId":"macie","region":"us-west-1","attributes":{"usageType":"Data Transfer","feature":"Security"},"pricePerUnit":"0.0032880000","unit":"USD per unit"},{"serviceId":"macie","region":"us-west-1","attributes":{"usageType":"Data Transfer","feature":"Security"},"pricePerUnit":"0.7800000000","unit":"USD per GB"},{"serviceId":"macie","region":"us-west-1","attributes":{"feature":"Security"},"pricePerUnit":"0.0000000000","unit":"USD per unit"},{"serviceId":"macie","region":"us-west-1","attributes":{"usageType":"Data Transfer","feature":"Security"},"pricePerUnit":"0.0000000000","unit":"USD per GB"},{"serviceId":"macie","region":"us-west-1","attributes":{"usageType":"Data Transfer","feature":"Security"},"pricePerUnit":"0.3900000000","unit":"USD per GB"},{"serviceId":"macie","region":"us-west-1","attributes":{"usageType":"Data Transfer","feature":"Security"},"pricePerUnit":"1.5500000000","unit":"USD per GB"},{"serviceId":"macie","region":"us-west-1","attributes":{"usageType":"Data Transfer","feature":"Tier"},"pricePerUnit":"0.0000000000","unit":"USD per GB"},{"serviceId":"macie","region":"us-east-2","attributes":{"feature":"Xtph"},"pricePerUnit":"0.0000000000","unit":"USD per unit"},{"serviceId":"macie","region":"us-east-2","attributes":{"feature":"Tdym"},"pricePerUnit":"0.0000000000","unit":"USD per unit"},{"serviceId":"macie","region":"us-east-2","attributes":{"feature":"Zvbyf"},"pricePerUnit":"1.0000000000","unit":"USD per unit"},{"serviceId":"macie","region":"us-east-2","attributes":{"feature":"Mjek"},"pricePerUnit":"0.0000000000","unit":"USD per unit"},{"serviceId":"macie","region":"us-east-2","attributes":{"usageType":"Data Transfer","feature":"Security"},"pricePerUnit":"0.0000000000","unit":"USD per unit"},{"serviceId":"macie","region":"us-east-2","attributes":{"usageType":"Data Transfer","feature":"Security"},"pricePerUnit":"0.0000000000","unit":"USD per unit"},{"serviceId":"macie","region":"us-east-2","attributes":{"feature":"Security"},"pricePerUnit":"0.0000000033","unit":"USD per unit"},{"serviceId":"macie","region":"us-east-2","attributes":{"feature":"Security"},"pricePerUnit":"0.0000000000","unit":"USD per unit"},{"serviceId":"macie","region":"us-east-2","attributes":{"usageType":"Data Transfer","feature":"Security"},"pricePerUnit":"0.0032880000","unit":"USD per unit"},{"serviceId":"macie","region":"us-east-2","attributes":{"usageType":"Data Transfer","feature":"Security"},"pricePerUnit":"0.0032880000","unit":"USD per unit"},{"serviceId":"macie","region":"us-east-2","attributes":{"usageType":"Data Transfer","feature":"Security"},"pricePerUnit":"0.5000000000","unit":"USD per GB"},{"serviceId":"macie","region":"us-east-2","attributes":{"feature":"Security"},"pricePerUnit":"0.0000000000","unit":"USD per unit"},{"serviceId":"macie","region":"us-east-2","attributes":{"usageType":"Data Transfer","feature":"Security"},"pricePerUnit":"0.0000000000","unit":"USD per GB"},{"serviceId":"macie","region":"us-east-2","attributes":{"usageType":"Data Transfer","feature":"Security"},"pricePerUnit":"0.2500000000","unit":"USD per GB"},{"serviceId":"macie","region":"us-east-2","attributes":{"usageType":"Data Transfer","feature":"Security"},"pricePerUnit":"1.0000000000","unit":"USD per GB"},{"serviceId":"macie","region":"us-east-2","attributes":{"usageType":"Data Transfer","feature":"Tier"},"pricePerUnit":"0.0000000000","unit":"USD per GB"},{"serviceId":"macie","region":"us-east-1","attributes":{"feature":"Xtph"},"pricePerUnit":"0.0000000000","unit":"USD per unit"},{"serviceId":"macie","region":"us-east-1","attributes":{"feature":"Tdym"},"pricePerUnit":"0.0000000000","unit":"USD per unit"},{"serviceId":"macie","region":"us-east-1","attributes":{"feature":"Zvbyf"},"pricePerUnit":"1.0000000000","unit":"USD per unit"},{"serviceId":"macie","region":"us-east-1","attributes":{"feature":"Mjek"},"pricePerUnit":"0.0000000000","unit":"USD per unit"},{"serviceId":"macie","region":"us-east-1","attributes":{"feature":"Pkdjm"},"pricePerUnit":"0.0000040000","unit":"USD per unit"},{"serviceId":"macie","region":"us-east-1","attributes":{"usageType":"Storage","feature":"Extended"},"pricePerUnit":"0.0500000000","unit":"USD per GB"},{"serviceId":"macie","region":"us-east-1","attributes":{"feature":"Tier"},"pricePerUnit":"0.0000000000","unit":"USD per GB"},{"serviceId":"macie","region":"us-east-1","attributes":{"feature":"Content"},"pricePerUnit":"0.0000000000","unit":"USD per GB"},{"serviceId":"macie","region":"us-east-1","attributes":{"feature":"Content"},"pricePerUnit":"0.0000000000","unit":"USD per GB"},{"serviceId":"macie","region":"us-east-1","attributes":{"usageType":"Data Transfer","feature":"Security"},"pricePerUnit":"0.0000000000","unit":"USD per unit"},{"serviceId":"macie","region":"us-east-1","attributes":{"usageType":"Data Transfer","feature":"Security"},"pricePerUnit":"0.0000000000","unit":"USD per unit"},{"serviceId":"macie","region":"us-east-1","attributes":{"feature":"Security"},"pricePerUnit":"0.0000000033","unit":"USD per unit"},{"serviceId":"macie","region":"us-east-1","attributes":{"feature":"Security"},"pricePerUnit":"0.0000000000","unit":"USD per unit"},{"serviceId":"macie","region":"us-east-1","attributes":{"usageType":"Data Transfer","feature":"Security"},"pricePerUnit":"0.0032880000","unit":"USD per unit"},{"serviceId":"macie","region":"us-east-1","attributes":{"usageType":"Data Transfer","feature":"Security"},"pricePerUnit":"0.0032880000","unit":"USD per unit"},{"serviceId":"macie","region":"us-east-1","attributes":{"usageType":"Data Transfer","feature":"Security"},"pricePerUnit":"0.5000000000","unit":"USD per GB"},{"serviceId":"macie","region":"us-east-1","attributes":{"feature":"Security"},"pricePerUnit":"0.0000000000","unit":"USD per unit"},{"serviceId":"macie","region":"us-east-1","attributes":{"usageType":"Data Transfer","feature":"Security"},"pricePerUnit":"0.0000000000","unit":"USD per GB"},{"serviceId":"macie","region":"us-east-1","attributes":{"usageType":"Data Transfer","feature":"Security"},"pricePerUnit":"0.2500000000","unit":"USD per GB"},{"serviceId":"macie","region":"us-east-1","attributes":{"usageType":"Data Transfer","feature":"Security"},"pricePerUnit":"1.0000000000","unit":"USD per GB"},{"serviceId":"macie","region":"us-east-1","attributes":{"usageType":"Data Transfer","feature":"Tier"},"pricePerUnit":"0.0000000000","unit":"USD per GB"},{"serviceId":"macie","region":"us-east-1","attributes":{"feature":"Cloud"},"pricePerUnit":"0.0000040000","unit":"USD per unit"},{"serviceId":"macie","region":"south-america-(sao-paulo)","attributes":{"feature":"Xtph"},"pricePerUnit":"0.0000000000","unit":"USD per unit"},{"serviceId":"macie","region":"south-america-(sao-paulo)","attributes":{"feature":"Tdym"},"pricePerUnit":"0.0000000000","unit":"USD per unit"},{"serviceId":"macie","region":"south-america-(sao-paulo)","attributes":{"feature":"Zvbyf"},"pricePerUnit":"2.2500000000","unit":"USD per unit"},{"serviceId":"macie","region":"south-america-(sao-paulo)","attributes":{"feature":"Mjek"},"pricePerUnit":"0.0000000000","unit":"USD per unit"},{"serviceId":"macie","region":"south-america-(sao-paulo)","attributes":{"usageType":"Data Transfer","feature":"Security"},"pricePerUnit":"0.0000000000","unit":"USD per unit"},{"serviceId":"macie","region":"south-america-(sao-paulo)","attributes":{"usageType":"Data Transfer","feature":"Security"},"pricePerUnit":"0.0000000000","unit":"USD per unit"},{"serviceId":"macie","region":"south-america-(sao-paulo)","attributes":{"feature":"Security"},"pricePerUnit":"0.0000000074","unit":"USD per unit"},{"serviceId":"macie","region":"south-america-(sao-paulo)","attributes":{"feature":"Security"},"pricePerUnit":"0.0000000000","unit":"USD per unit"},{"serviceId":"macie","region":"south-america-(sao-paulo)","attributes":{"usageType":"Data Transfer","feature":"Security"},"pricePerUnit":"0.0032880000","unit":"USD per unit"},{"serviceId":"macie","region":"south-america-(sao-paulo)","attributes":{"usageType":"Data Transfer","feature":"Security"},"pricePerUnit":"0.0032880000","unit":"USD per unit"},{"serviceId":"macie","region":"south-america-(sao-paulo)","attributes":{"usageType":"Data Transfer","feature":"Security"},"pricePerUnit":"1.1300000000","unit":"USD per GB"},{"serviceId":"macie","region":"south-america-(sao-paulo)","attributes":{"feature":"Security"},"pricePerUnit":"0.0000000000","unit":"USD per unit"},{"serviceId":"macie","region":"south-america-(sao-paulo)","attributes":{"usageType":"Data Transfer","feature":"Security"},"pricePerUnit":"0.0000000000","unit":"USD per GB"},{"serviceId":"macie","region":"south-america-(sao-paulo)","attributes":{"usageType":"Data Transfer","feature":"Security"},"pricePerUnit":"0.5600000000","unit":"USD per GB"},{"serviceId":"macie","region":"south-america-(sao-paulo)","attributes":{"usageType":"Data Transfer","feature":"Security"},"pricePerUnit":"2.2500000000","unit":"USD per GB"},{"serviceId":"macie","region":"south-america-(sao-paulo)","attributes":{"usageType":"Data Transfer","feature":"Tier"},"pricePerUnit":"0.0000000000","unit":"USD per GB"},{"serviceId":"macie","region":"middle-east-(bahrain)","attributes":{"feature":"Xtph"},"pricePerUnit":"0.0000000000","unit":"USD per unit"},{"serviceId":"macie","region":"middle-east-(bahrain)","attributes":{"feature":"Tdym"},"pricePerUnit":"0.0000000000","unit":"USD per unit"},{"serviceId":"macie","region":"middle-east-(bahrain)","attributes":{"feature":"Zvbyf"},"pricePerUnit":"1.4000000000","unit":"USD per unit"},{"serviceId":"macie","region":"middle-east-(bahrain)","attributes":{"feature":"Mjek"},"pricePerUnit":"0.0000000000","unit":"USD per unit"},{"serviceId":"macie","region":"middle-east-(bahrain)","attributes":{"usageType":"Data Transfer","feature":"Security"},"pricePerUnit":"0.0000000000","unit":"USD per unit"},{"serviceId":"macie","region":"middle-east-(bahrain)","attributes":{"usageType":"Data Transfer","feature":"Security"},"pricePerUnit":"0.0000000000","unit":"USD per unit"},{"serviceId":"macie","region":"middle-east-(bahrain)","attributes":{"feature":"Security"},"pricePerUnit":"0.0000000046","unit":"USD per unit"},{"serviceId":"macie","region":"middle-east-(bahrain)","attributes":{"feature":"Security"},"pricePerUnit":"0.0000000000","unit":"USD per unit"},{"serviceId":"macie","region":"middle-east-(bahrain)","attributes":{"usageType":"Data Transfer","feature":"Security"},"pricePerUnit":"0.0032880000","unit":"USD per unit"},{"serviceId":"macie","region":"middle-east-(bahrain)","attributes":{"usageType":"Data Transfer","feature":"Security"},"pricePerUnit":"0.0032880000","unit":"USD per unit"},{"serviceId":"macie","region":"middle-east-(bahrain)","attributes":{"usageType":"Data Transfer","feature":"Security"},"pricePerUnit":"0.7000000000","unit":"USD per GB"},{"serviceId":"macie","region":"middle-east-(bahrain)","attributes":{"feature":"Security"},"pricePerUnit":"0.0000000000","unit":"USD per unit"},{"serviceId":"macie","region":"middle-east-(bahrain)","attributes":{"usageType":"Data Transfer","feature":"Security"},"pricePerUnit":"0.0000000000","unit":"USD per GB"},{"serviceId":"macie","region":"middle-east-(bahrain)","attributes":{"usageType":"Data Transfer","feature":"Security"},"pricePerUnit":"0.3500000000","unit":"USD per GB"},{"serviceId":"macie","region":"middle-east-(bahrain)","attributes":{"usageType":"Data Transfer","feature":"Security"},"pricePerUnit":"1.4000000000","unit":"USD per GB"},{"serviceId":"macie","region":"middle-east-(bahrain)","attributes":{"usageType":"Data Transfer","feature":"Tier"},"pricePerUnit":"0.0000000000","unit":"USD per GB"},{"serviceId":"macie","region":"israel-(tel-aviv)","attributes":{"feature":"Xtph"},"pricePerUnit":"0.0000000000","unit":"USD per unit"},{"serviceId":"macie","region":"israel-(tel-aviv)","attributes":{"feature":"Tdym"},"pricePerUnit":"0.0000000000","unit":"USD per unit"},{"serviceId":"macie","region":"israel-(tel-aviv)","attributes":{"feature":"Zvbyf"},"pricePerUnit":"1.2800000000","unit":"USD per unit"},{"serviceId":"macie","region":"israel-(tel-aviv)","attributes":{"feature":"Mjek"},"pricePerUnit":"0.0000000000","unit":"USD per unit"},{"serviceId":"macie","region":"israel-(tel-aviv)","attributes":{"usageType":"Data Transfer","feature":"Security"},"pricePerUnit":"0.0000000000","unit":"USD per unit"},{"serviceId":"macie","region":"israel-(tel-aviv)","attributes":{"usageType":"Data Transfer","feature":"Security"},"pricePerUnit":"0.0000000000","unit":"USD per unit"},{"serviceId":"macie","region":"israel-(tel-aviv)","attributes":{"feature":"Security"},"pricePerUnit":"0.0000000042","unit":"USD per unit"},{"serviceId":"macie","region":"israel-(tel-aviv)","attributes":{"feature":"Security"},"pricePerUnit":"0.0000000000","unit":"USD per unit"},{"serviceId":"macie","region":"israel-(tel-aviv)","attributes":{"usageType":"Data Transfer","feature":"Security"},"pricePerUnit":"0.0042086400","unit":"USD per unit"},{"serviceId":"macie","region":"israel-(tel-aviv)","attributes":{"usageType":"Data Transfer","feature":"Security"},"pricePerUnit":"0.0042086400","unit":"USD per unit"},{"serviceId":"macie","region":"israel-(tel-aviv)","attributes":{"usageType":"Data Transfer","feature":"Security"},"pricePerUnit":"0.6400000000","unit":"USD per GB"},{"serviceId":"macie","region":"israel-(tel-aviv)","attributes":{"feature":"Security"},"pricePerUnit":"0.0000000000","unit":"USD per unit"},{"serviceId":"macie","region":"israel-(tel-aviv)","attributes":{"usageType":"Data Transfer","feature":"Security"},"pricePerUnit":"0.0000000000","unit":"USD per GB"},{"serviceId":"macie","region":"israel-(tel-aviv)","attributes":{"usageType":"Data Transfer","feature":"Security"},"pricePerUnit":"0.3200000000","unit":"USD per GB"},{"serviceId":"macie","region":"israel-(tel-aviv)","attributes":{"usageType":"Data Transfer","feature":"Security"},"pricePerUnit":"1.2800000000","unit":"USD per GB"},{"serviceId":"macie","region":"israel-(tel-aviv)","attributes":{"usageType":"Data Transfer","feature":"Tier"},"pricePerUnit":"0.0000000000","unit":"USD per GB"},{"serviceId":"macie","region":"eu-(stockholm)","attributes":{"feature":"Xtph"},"pricePerUnit":"0.0000000000","unit":"USD per unit"},{"serviceId":"macie","region":"eu-(stockholm)","attributes":{"feature":"Tdym"},"pricePerUnit":"0.0000000000","unit":"USD per unit"},{"serviceId":"macie","region":"eu-(stockholm)","attributes":{"feature":"Zvbyf"},"pricePerUnit":"1.0000000000","unit":"USD per unit"},{"serviceId":"macie","region":"eu-(stockholm)","attributes":{"feature":"Mjek"},"pricePerUnit":"0.0000000000","unit":"USD per unit"},{"serviceId":"macie","region":"eu-(stockholm)","attributes":{"usageType":"Data Transfer","feature":"Security"},"pricePerUnit":"0.0000000000","unit":"USD per unit"},{"serviceId":"macie","region":"eu-(stockholm)","attributes":{"usageType":"Data Transfer","feature":"Security"},"pricePerUnit":"0.0000000000","unit":"USD per unit"},{"serviceId":"macie","region":"eu-(stockholm)","attributes":{"feature":"Security"},"pricePerUnit":"0.0000000033","unit":"USD per unit"},{"serviceId":"macie","region":"eu-(stockholm)","attributes":{"feature":"Security"},"pricePerUnit":"0.0000000000","unit":"USD per unit"},{"serviceId":"macie","region":"eu-(stockholm)","attributes":{"usageType":"Data Transfer","feature":"Security"},"pricePerUnit":"0.0032880000","unit":"USD per unit"},{"serviceId":"macie","region":"eu-(stockholm)","attributes":{"usageType":"Data Transfer","feature":"Security"},"pricePerUnit":"0.0032880000","unit":"USD per unit"},{"serviceId":"macie","region":"eu-(stockholm)","attributes":{"usageType":"Data Transfer","feature":"Security"},"pricePerUnit":"0.5000000000","unit":"USD per GB"},{"serviceId":"macie","region":"eu-(stockholm)","attributes":{"feature":"Security"},"pricePerUnit":"0.0000000000","unit":"USD per unit"},{"serviceId":"macie","region":"eu-(stockholm)","attributes":{"usageType":"Data Transfer","feature":"Security"},"pricePerUnit":"0.0000000000","unit":"USD per GB"},{"serviceId":"macie","region":"eu-(stockholm)","attributes":{"usageType":"Data Transfer","feature":"Security"},"pricePerUnit":"0.2500000000","unit":"USD per GB"},{"serviceId":"macie","region":"eu-(stockholm)","attributes":{"usageType":"Data Transfer","feature":"Security"},"pricePerUnit":"1.0000000000","unit":"USD per GB"},{"serviceId":"macie","region":"eu-(stockholm)","attributes":{"usageType":"Data Transfer","feature":"Tier"},"pricePerUnit":"0.0000000000","unit":"USD per GB"},{"serviceId":"macie","region":"eu-(paris)","attributes":{"feature":"Xtph"},"pricePerUnit":"0.0000000000","unit":"USD per unit"},{"serviceId":"macie","region":"eu-(paris)","attributes":{"feature":"Tdym"},"pricePerUnit":"0.0000000000","unit":"USD per unit"},{"serviceId":"macie","region":"eu-(paris)","attributes":{"feature":"Zvbyf"},"pricePerUnit":"1.2500000000","unit":"USD per unit"},{"serviceId":"macie","region":"eu-(paris)","attributes":{"feature":"Mjek"},"pricePerUnit":"0.0000000000","unit":"USD per unit"},{"serviceId":"macie","region":"eu-(paris)","attributes":{"usageType":"Data Transfer","feature":"Security"},"pricePerUnit":"0.0000000000","unit":"USD per unit"},{"serviceId":"macie","region":"eu-(paris)","attributes":{"usageType":"Data Transfer","feature":"Security"},"pricePerUnit":"0.0000000000","unit":"USD per unit"},{"serviceId":"macie","region":"eu-(paris)","attributes":{"feature":"Security"},"pricePerUnit":"0.0000000041","unit":"USD per unit"},{"serviceId":"macie","region":"eu-(paris)","attributes":{"feature":"Security"},"pricePerUnit":"0.0000000000","unit":"USD per unit"},{"serviceId":"macie","region":"eu-(paris)","attributes":{"usageType":"Data Transfer","feature":"Security"},"pricePerUnit":"0.0032880000","unit":"USD per unit"},{"serviceId":"macie","region":"eu-(paris)","attributes":{"usageType":"Data Transfer","feature":"Security"},"pricePerUnit":"0.0032880000","unit":"USD per unit"},{"serviceId":"macie","region":"eu-(paris)","attributes":{"usageType":"Data Transfer","feature":"Security"},"pricePerUnit":"0.6300000000","unit":"USD per GB"},{"serviceId":"macie","region":"eu-(paris)","attributes":{"feature":"Security"},"pricePerUnit":"0.0000000000","unit":"USD per unit"},{"serviceId":"macie","region":"eu-(paris)","attributes":{"usageType":"Data Transfer","feature":"Security"},"pricePerUnit":"0.0000000000","unit":"USD per GB"},{"serviceId":"macie","region":"eu-(paris)","attributes":{"usageType":"Data Transfer","feature":"Security"},"pricePerUnit":"0.3100000000","unit":"USD per GB"},{"serviceId":"macie","region":"eu-(paris)","attributes":{"usageType":"Data Transfer","feature":"Security"},"pricePerUnit":"1.2500000000","unit":"USD per GB"},{"serviceId":"macie","region":"eu-(paris)","attributes":{"usageType":"Data Transfer","feature":"Tier"},"pricePerUnit":"0.0000000000","unit":"USD per GB"},{"serviceId":"macie","region":"eu-(milan)","attributes":{"feature":"Xtph"},"pricePerUnit":"0.0000000000","unit":"USD per unit"},{"serviceId":"macie","region":"eu-(milan)","attributes":{"feature":"Tdym"},"pricePerUnit":"0.0000000000","unit":"USD per unit"},{"serviceId":"macie","region":"eu-(milan)","attributes":{"feature":"Zvbyf"},"pricePerUnit":"1.5500000000","unit":"USD per unit"},{"serviceId":"macie","region":"eu-(milan)","attributes":{"feature":"Mjek"},"pricePerUnit":"0.0000000000","unit":"USD per unit"},{"serviceId":"macie","region":"eu-(milan)","attributes":{"usageType":"Data Transfer","feature":"Security"},"pricePerUnit":"0.0000000000","unit":"USD per unit"},{"serviceId":"macie","region":"eu-(milan)","attributes":{"usageType":"Data Transfer","feature":"Security"},"pricePerUnit":"0.0000000000","unit":"USD per unit"},{"serviceId":"macie","region":"eu-(milan)","attributes":{"feature":"Security"},"pricePerUnit":"0.0000000051","unit":"USD per unit"},{"serviceId":"macie","region":"eu-(milan)","attributes":{"feature":"Security"},"pricePerUnit":"0.0000000000","unit":"USD per unit"},{"serviceId":"macie","region":"eu-(milan)","attributes":{"usageType":"Data Transfer","feature":"Security"},"pricePerUnit":"0.0032880000","unit":"USD per unit"},{"serviceId":"macie","region":"eu-(milan)","attributes":{"usageType":"Data Transfer","feature":"Security"},"pricePerUnit":"0.0032880000","unit":"USD per unit"},{"serviceId":"macie","region":"eu-(milan)","attributes":{"usageType":"Data Transfer","feature":"Security"},"pricePerUnit":"0.7800000000","unit":"USD per GB"},{"serviceId":"macie","region":"eu-(milan)","attributes":{"feature":"Security"},"pricePerUnit":"0.0000000000","unit":"USD per unit"},{"serviceId":"macie","region":"eu-(milan)","attributes":{"usageType":"Data Transfer","feature":"Security"},"pricePerUnit":"0.0000000000","unit":"USD per GB"},{"serviceId":"macie","region":"eu-(milan)","attributes":{"usageType":"Data Transfer","feature":"Security"},"pricePerUnit":"0.3900000000","unit":"USD per GB"},{"serviceId":"macie","region":"eu-(milan)","attributes":{"usageType":"Data Transfer","feature":"Security"},"pricePerUnit":"1.5500000000","unit":"USD per GB"},{"serviceId":"macie","region":"eu-(milan)","attributes":{"usageType":"Data Transfer","feature":"Tier"},"pricePerUnit":"0.0000000000","unit":"USD per GB"},{"serviceId":"macie","region":"eu-west-2","attributes":{"feature":"Xtph"},"pricePerUnit":"0.0000000000","unit":"USD per unit"},{"serviceId":"macie","region":"eu-west-2","attributes":{"feature":"Tdym"},"pricePerUnit":"0.0000000000","unit":"USD per unit"},{"serviceId":"macie","region":"eu-west-2","attributes":{"feature":"Zvbyf"},"pricePerUnit":"1.2500000000","unit":"USD per unit"},{"serviceId":"macie","region":"eu-west-2","attributes":{"feature":"Mjek"},"pricePerUnit":"0.0000000000","unit":"USD per unit"},{"serviceId":"macie","region":"eu-west-2","attributes":{"usageType":"Data Transfer","feature":"Security"},"pricePerUnit":"0.0000000000","unit":"USD per unit"},{"serviceId":"macie","region":"eu-west-2","attributes":{"usageType":"Data Transfer","feature":"Security"},"pricePerUnit":"0.0000000000","unit":"USD per unit"},{"serviceId":"macie","region":"eu-west-2","attributes":{"feature":"Security"},"pricePerUnit":"0.0000000041","unit":"USD per unit"},{"serviceId":"macie","region":"eu-west-2","attributes":{"feature":"Security"},"pricePerUnit":"0.0000000000","unit":"USD per unit"},{"serviceId":"macie","region":"eu-west-2","attributes":{"usageType":"Data Transfer","feature":"Security"},"pricePerUnit":"0.0032880000","unit":"USD per unit"},{"serviceId":"macie","region":"eu-west-2","attributes":{"usageType":"Data Transfer","feature":"Security"},"pricePerUnit":"0.0032880000","unit":"USD per unit"},{"serviceId":"macie","region":"eu-west-2","attributes":{"usageType":"Data Transfer","feature":"Security"},"pricePerUnit":"0.6300000000","unit":"USD per GB"},{"serviceId":"macie","region":"eu-west-2","attributes":{"feature":"Security"},"pricePerUnit":"0.0000000000","unit":"USD per unit"},{"serviceId":"macie","region":"eu-west-2","attributes":{"usageType":"Data Transfer","feature":"Security"},"pricePerUnit":"0.0000000000","unit":"USD per GB"},{"serviceId":"macie","region":"eu-west-2","attributes":{"usageType":"Data Transfer","feature":"Security"},"pricePerUnit":"0.3100000000","unit":"USD per GB"},{"serviceId":"macie","region":"eu-west-2","attributes":{"usageType":"Data Transfer","feature":"Security"},"pricePerUnit":"1.2500000000","unit":"USD per GB"},{"serviceId":"macie","region":"eu-west-2","attributes":{"usageType":"Data Transfer","feature":"Tier"},"pricePerUnit":"0.0000000000","unit":"USD per GB"},{"serviceId":"macie","region":"eu-west-1","attributes":{"feature":"Xtph"},"pricePerUnit":"0.0000000000","unit":"USD per unit"},{"serviceId":"macie","region":"eu-west-1","attributes":{"feature":"Tdym"},"pricePerUnit":"0.0000000000","unit":"USD per unit"},{"serviceId":"macie","region":"eu-west-1","attributes":{"feature":"Zvbyf"},"pricePerUnit":"1.0000000000","unit":"USD per unit"},{"serviceId":"macie","region":"eu-west-1","attributes":{"feature":"Mjek"},"pricePerUnit":"0.0000000000","unit":"USD per unit"},{"serviceId":"macie","region":"eu-west-1","attributes":{"usageType":"Data Transfer","feature":"Security"},"pricePerUnit":"0.0000000000","unit":"USD per unit"},{"serviceId":"macie","region":"eu-west-1","attributes":{"usageType":"Data Transfer","feature":"Security"},"pricePerUnit":"0.0000000000","unit":"USD per unit"},{"serviceId":"macie","region":"eu-west-1","attributes":{"feature":"Security"},"pricePerUnit":"0.0000000033","unit":"USD per unit"},{"serviceId":"macie","region":"eu-west-1","attributes":{"feature":"Security"},"pricePerUnit":"0.0000000000","unit":"USD per unit"},{"serviceId":"macie","region":"eu-west-1","attributes":{"usageType":"Data Transfer","feature":"Security"},"pricePerUnit":"0.0032880000","unit":"USD per unit"},{"serviceId":"macie","region":"eu-west-1","attributes":{"usageType":"Data Transfer","feature":"Security"},"pricePerUnit":"0.0032880000","unit":"USD per unit"},{"serviceId":"macie","region":"eu-west-1","attributes":{"usageType":"Data Transfer","feature":"Security"},"pricePerUnit":"0.5000000000","unit":"USD per GB"},{"serviceId":"macie","region":"eu-west-1","attributes":{"feature":"Security"},"pricePerUnit":"0.0000000000","unit":"USD per unit"},{"serviceId":"macie","region":"eu-west-1","attributes":{"usageType":"Data Transfer","feature":"Security"},"pricePerUnit":"0.0000000000","unit":"USD per GB"},{"serviceId":"macie","region":"eu-west-1","attributes":{"usageType":"Data Transfer","feature":"Security"},"pricePerUnit":"0.2500000000","unit":"USD per GB"},{"serviceId":"macie","region":"eu-west-1","attributes":{"usageType":"Data Transfer","feature":"Security"},"pricePerUnit":"1.0000000000","unit":"USD per GB"},{"serviceId":"macie","region":"eu-west-1","attributes":{"usageType":"Data Transfer","feature":"Tier"},"pricePerUnit":"0.0000000000","unit":"USD per GB"},{"serviceId":"macie","region":"eu-central-1","attributes":{"feature":"Xtph"},"pricePerUnit":"0.0000000000","unit":"USD per unit"},{"serviceId":"macie","region":"eu-central-1","attributes":{"feature":"Tdym"},"pricePerUnit":"0.0000000000","unit":"USD per unit"},{"serviceId":"macie","region":"eu-central-1","attributes":{"feature":"Zvbyf"},"pricePerUnit":"1.2500000000","unit":"USD per unit"},{"serviceId":"macie","region":"eu-central-1","attributes":{"feature":"Mjek"},"pricePerUnit":"0.0000000000","unit":"USD per unit"},{"serviceId":"macie","region":"eu-central-1","attributes":{"usageType":"Data Transfer","feature":"Security"},"pricePerUnit":"0.0000000000","unit":"USD per unit"},{"serviceId":"macie","region":"eu-central-1","attributes":{"usageType":"Data Transfer","feature":"Security"},"pricePerUnit":"0.0000000000","unit":"USD per unit"},{"serviceId":"macie","region":"eu-central-1","attributes":{"feature":"Security"},"pricePerUnit":"0.0000000041","unit":"USD per unit"},{"serviceId":"macie","region":"eu-central-1","attributes":{"feature":"Security"},"pricePerUnit":"0.0000000000","unit":"USD per unit"},{"serviceId":"macie","region":"eu-central-1","attributes":{"usageType":"Data Transfer","feature":"Security"},"pricePerUnit":"0.0032880000","unit":"USD per unit"},{"serviceId":"macie","region":"eu-central-1","attributes":{"usageType":"Data Transfer","feature":"Security"},"pricePerUnit":"0.0032880000","unit":"USD per unit"},{"serviceId":"macie","region":"eu-central-1","attributes":{"usageType":"Data Transfer","feature":"Security"},"pricePerUnit":"0.6300000000","unit":"USD per GB"},{"serviceId":"macie","region":"eu-central-1","attributes":{"feature":"Security"},"pricePerUnit":"0.0000000000","unit":"USD per unit"},{"serviceId":"macie","region":"eu-central-1","attributes":{"usageType":"Data Transfer","feature":"Security"},"pricePerUnit":"0.0000000000","unit":"USD per GB"},{"serviceId":"macie","region":"eu-central-1","attributes":{"usageType":"Data Transfer","feature":"Security"},"pricePerUnit":"0.3100000000","unit":"USD per GB"},{"serviceId":"macie","region":"eu-central-1","attributes":{"usageType":"Data Transfer","feature":"Security"},"pricePerUnit":"1.2500000000","unit":"USD per GB"},{"serviceId":"macie","region":"eu-central-1","attributes":{"usageType":"Data Transfer","feature":"Tier"},"pricePerUnit":"0.0000000000","unit":"USD per GB"},{"serviceId":"macie","region":"canada-(central)","attributes":{"feature":"Xtph"},"pricePerUnit":"0.0000000000","unit":"USD per unit"},{"serviceId":"macie","region":"canada-(central)","attributes":{"feature":"Tdym"},"pricePerUnit":"0.0000000000","unit":"USD per unit"},{"serviceId":"macie","region":"canada-(central)","attributes":{"feature":"Zvbyf"},"pricePerUnit":"1.1500000000","unit":"USD per unit"},{"serviceId":"macie","region":"canada-(central)","attributes":{"feature":"Mjek"},"pricePerUnit":"0.0000000000","unit":"USD per unit"},{"serviceId":"macie","region":"canada-(central)","attributes":{"usageType":"Data Transfer","feature":"Security"},"pricePerUnit":"0.0000000000","unit":"USD per unit"},{"serviceId":"macie","region":"canada-(central)","attributes":{"usageType":"Data Transfer","feature":"Security"},"pricePerUnit":"0.0000000000","unit":"USD per unit"},{"serviceId":"macie","region":"canada-(central)","attributes":{"feature":"Security"},"pricePerUnit":"0.0000000038","unit":"USD per unit"},{"serviceId":"macie","region":"canada-(central)","attributes":{"feature":"Security"},"pricePerUnit":"0.0000000000","unit":"USD per unit"},{"serviceId":"macie","region":"canada-(central)","attributes":{"usageType":"Data Transfer","feature":"Security"},"pricePerUnit":"0.0032880000","unit":"USD per unit"},{"serviceId":"macie","region":"canada-(central)","attributes":{"usageType":"Data Transfer","feature":"Security"},"pricePerUnit":"0.0032880000","unit":"USD per unit"},{"serviceId":"macie","region":"canada-(central)","attributes":{"usageType":"Data Transfer","feature":"Security"},"pricePerUnit":"0.5800000000","unit":"USD per GB"},{"serviceId":"macie","region":"canada-(central)","attributes":{"feature":"Security"},"pricePerUnit":"0.0000000000","unit":"USD per unit"},{"serviceId":"macie","region":"canada-(central)","attributes":{"usageType":"Data Transfer","feature":"Security"},"pricePerUnit":"0.0000000000","unit":"USD per GB"},{"serviceId":"macie","region":"canada-(central)","attributes":{"usageType":"Data Transfer","feature":"Security"},"pricePerUnit":"0.2900000000","unit":"USD per GB"},{"serviceId":"macie","region":"canada-(central)","attributes":{"usageType":"Data Transfer","feature":"Security"},"pricePerUnit":"1.1500000000","unit":"USD per GB"},{"serviceId":"macie","region":"canada-(central)","attributes":{"usageType":"Data Transfer","feature":"Tier"},"pricePerUnit":"0.0000000000","unit":"USD per GB"},{"serviceId":"macie","region":"ap-northeast-1","attributes":{"feature":"Xtph"},"pricePerUnit":"0.0000000000","unit":"USD per unit"},{"serviceId":"macie","region":"ap-northeast-1","attributes":{"feature":"Tdym"},"pricePerUnit":"0.0000000000","unit":"USD per unit"},{"serviceId":"macie","region":"ap-northeast-1","attributes":{"feature":"Zvbyf"},"pricePerUnit":"1.2500000000","unit":"USD per unit"},{"serviceId":"macie","region":"ap-northeast-1","attributes":{"feature":"Mjek"},"pricePerUnit":"0.0000000000","unit":"USD per unit"},{"serviceId":"macie","region":"ap-northeast-1","attributes":{"usageType":"Data Transfer","feature":"Security"},"pricePerUnit":"0.0000000000","unit":"USD per unit"},{"serviceId":"macie","region":"ap-northeast-1","attributes":{"usageType":"Data Transfer","feature":"Security"},"pricePerUnit":"0.0000000000","unit":"USD per unit"},{"serviceId":"macie","region":"ap-northeast-1","attributes":{"feature":"Security"},"pricePerUnit":"0.0000000041","unit":"USD per unit"},{"serviceId":"macie","region":"ap-northeast-1","attributes":{"feature":"Security"},"pricePerUnit":"0.0000000000","unit":"USD per unit"},{"serviceId":"macie","region":"ap-northeast-1","attributes":{"usageType":"Data Transfer","feature":"Security"},"pricePerUnit":"0.0032880000","unit":"USD per unit"},{"serviceId":"macie","region":"ap-northeast-1","attributes":{"usageType":"Data Transfer","feature":"Security"},"pricePerUnit":"0.0032880000","unit":"USD per unit"},{"serviceId":"macie","region":"ap-northeast-1","attributes":{"usageType":"Data Transfer","feature":"Security"},"pricePerUnit":"0.6300000000","unit":"USD per GB"},{"serviceId":"macie","region":"ap-northeast-1","attributes":{"feature":"Security"},"pricePerUnit":"0.0000000000","unit":"USD per unit"},{"serviceId":"macie","region":"ap-northeast-1","attributes":{"usageType":"Data Transfer","feature":"Security"},"pricePerUnit":"0.0000000000","unit":"USD per GB"},{"serviceId":"macie","region":"ap-northeast-1","attributes":{"usageType":"Data Transfer","feature":"Security"},"pricePerUnit":"0.3100000000","unit":"USD per GB"},{"serviceId":"macie","region":"ap-northeast-1","attributes":{"usageType":"Data Transfer","feature":"Security"},"pricePerUnit":"1.2500000000","unit":"USD per GB"},{"serviceId":"macie","region":"ap-northeast-1","attributes":{"usageType":"Data Transfer","feature":"Tier"},"pricePerUnit":"0.0000000000","unit":"USD per GB"},{"serviceId":"macie","region":"ap-southeast-2","attributes":{"feature":"Xtph"},"pricePerUnit":"0.0000000000","unit":"USD per unit"},{"serviceId":"macie","region":"ap-southeast-2","attributes":{"feature":"Tdym"},"pricePerUnit":"0.0000000000","unit":"USD per unit"},{"serviceId":"macie","region":"ap-southeast-2","attributes":{"feature":"Zvbyf"},"pricePerUnit":"1.2500000000","unit":"USD per unit"},{"serviceId":"macie","region":"ap-southeast-2","attributes":{"feature":"Mjek"},"pricePerUnit":"0.0000000000","unit":"USD per unit"},{"serviceId":"macie","region":"ap-southeast-2","attributes":{"usageType":"Data Transfer","feature":"Security"},"pricePerUnit":"0.0000000000","unit":"USD per unit"},{"serviceId":"macie","region":"ap-southeast-2","attributes":{"usageType":"Data Transfer","feature":"Security"},"pricePerUnit":"0.0000000000","unit":"USD per unit"},{"serviceId":"macie","region":"ap-southeast-2","attributes":{"feature":"Security"},"pricePerUnit":"0.0000000041","unit":"USD per unit"},{"serviceId":"macie","region":"ap-southeast-2","attributes":{"feature":"Security"},"pricePerUnit":"0.0000000000","unit":"USD per unit"},{"serviceId":"macie","region":"ap-southeast-2","attributes":{"usageType":"Data Transfer","feature":"Security"},"pricePerUnit":"0.0032880000","unit":"USD per unit"},{"serviceId":"macie","region":"ap-southeast-2","attributes":{"usageType":"Data Transfer","feature":"Security"},"pricePerUnit":"0.0032880000","unit":"USD per unit"},{"serviceId":"macie","region":"ap-southeast-2","attributes":{"usageType":"Data Transfer","feature":"Security"},"pricePerUnit":"0.6300000000","unit":"USD per GB"},{"serviceId":"macie","region":"ap-southeast-2","attributes":{"feature":"Security"},"pricePerUnit":"0.0000000000","unit":"USD per unit"},{"serviceId":"macie","region":"ap-southeast-2","attributes":{"usageType":"Data Transfer","feature":"Security"},"pricePerUnit":"0.0000000000","unit":"USD per GB"},{"serviceId":"macie","region":"ap-southeast-2","attributes":{"usageType":"Data Transfer","feature":"Security"},"pricePerUnit":"0.3100000000","unit":"USD per GB"},{"serviceId":"macie","region":"ap-southeast-2","attributes":{"usageType":"Data Transfer","feature":"Security"},"pricePerUnit":"1.2500000000","unit":"USD per GB"},{"serviceId":"macie","region":"ap-southeast-2","attributes":{"usageType":"Data Transfer","feature":"Tier"},"pricePerUnit":"0.0000000000","unit":"USD per GB"},{"serviceId":"macie","region":"ap-southeast-1","attributes":{"feature":"Xtph"},"pricePerUnit":"0.0000000000","unit":"USD per unit"},{"serviceId":"macie","region":"ap-southeast-1","attributes":{"feature":"Tdym"},"pricePerUnit":"0.0000000000","unit":"USD per unit"},{"serviceId":"macie","region":"ap-southeast-1","attributes":{"feature":"Zvbyf"},"pricePerUnit":"1.3500000000","unit":"USD per unit"},{"serviceId":"macie","region":"ap-southeast-1","attributes":{"feature":"Mjek"},"pricePerUnit":"0.0000000000","unit":"USD per unit"},{"serviceId":"macie","region":"ap-southeast-1","attributes":{"usageType":"Data Transfer","feature":"Security"},"pricePerUnit":"0.0000000000","unit":"USD per unit"},{"serviceId":"macie","region":"ap-southeast-1","attributes":{"usageType":"Data Transfer","feature":"Security"},"pricePerUnit":"0.0000000000","unit":"USD per unit"},{"serviceId":"macie","region":"ap-southeast-1","attributes":{"feature":"Security"},"pricePerUnit":"0.0000000044","unit":"USD per unit"},{"serviceId":"macie","region":"ap-southeast-1","attributes":{"feature":"Security"},"pricePerUnit":"0.0000000000","unit":"USD per unit"},{"serviceId":"macie","region":"ap-southeast-1","attributes":{"usageType":"Data Transfer","feature":"Security"},"pricePerUnit":"0.0032880000","unit":"USD per unit"},{"serviceId":"macie","region":"ap-southeast-1","attributes":{"usageType":"Data Transfer","feature":"Security"},"pricePerUnit":"0.0032880000","unit":"USD per unit"},{"serviceId":"macie","region":"ap-southeast-1","attributes":{"usageType":"Data Transfer","feature":"Security"},"pricePerUnit":"0.6800000000","unit":"USD per GB"},{"serviceId":"macie","region":"ap-southeast-1","attributes":{"feature":"Security"},"pricePerUnit":"0.0000000000","unit":"USD per unit"},{"serviceId":"macie","region":"ap-southeast-1","attributes":{"usageType":"Data Transfer","feature":"Security"},"pricePerUnit":"0.0000000000","unit":"USD per GB"},{"serviceId":"macie","region":"ap-southeast-1","attributes":{"usageType":"Data Transfer","feature":"Security"},"pricePerUnit":"0.3400000000","unit":"USD per GB"},{"serviceId":"macie","region":"ap-southeast-1","attributes":{"usageType":"Data Transfer","feature":"Security"},"pricePerUnit":"1.3500000000","unit":"USD per GB"},{"serviceId":"macie","region":"ap-southeast-1","attributes":{"usageType":"Data Transfer","feature":"Tier"},"pricePerUnit":"0.0000000000","unit":"USD per GB"},{"serviceId":"macie","region":"asia-pacific-(seoul)","attributes":{"feature":"Xtph"},"pricePerUnit":"0.0000000000","unit":"USD per unit"},{"serviceId":"macie","region":"asia-pacific-(seoul)","attributes":{"feature":"Tdym"},"pricePerUnit":"0.0000000000","unit":"USD per unit"},{"serviceId":"macie","region":"asia-pacific-(seoul)","attributes":{"feature":"Zvbyf"},"pricePerUnit":"1.1500000000","unit":"USD per unit"},{"serviceId":"macie","region":"asia-pacific-(seoul)","attributes":{"feature":"Mjek"},"pricePerUnit":"0.0000000000","unit":"USD per unit"},{"serviceId":"macie","region":"asia-pacific-(seoul)","attributes":{"usageType":"Data Transfer","feature":"Security"},"pricePerUnit":"0.0000000000","unit":"USD per unit"},{"serviceId":"macie","region":"asia-pacific-(seoul)","attributes":{"usageType":"Data Transfer","feature":"Security"},"pricePerUnit":"0.0000000000","unit":"USD per unit"},{"serviceId":"macie","region":"asia-pacific-(seoul)","attributes":{"feature":"Security"},"pricePerUnit":"0.0000000038","unit":"USD per unit"},{"serviceId":"macie","region":"asia-pacific-(seoul)","attributes":{"feature":"Security"},"pricePerUnit":"0.0000000000","unit":"USD per unit"},{"serviceId":"macie","region":"asia-pacific-(seoul)","attributes":{"usageType":"Data Transfer","feature":"Security"},"pricePerUnit":"0.0032880000","unit":"USD per unit"},{"serviceId":"macie","region":"asia-pacific-(seoul)","attributes":{"usageType":"Data Transfer","feature":"Security"},"pricePerUnit":"0.0032880000","unit":"USD per unit"},{"serviceId":"macie","region":"asia-pacific-(seoul)","attributes":{"usageType":"Data Transfer","feature":"Security"},"pricePerUnit":"0.5800000000","unit":"USD per GB"},{"serviceId":"macie","region":"asia-pacific-(seoul)","attributes":{"feature":"Security"},"pricePerUnit":"0.0000000000","unit":"USD per unit"},{"serviceId":"macie","region":"asia-pacific-(seoul)","attributes":{"usageType":"Data Transfer","feature":"Security"},"pricePerUnit":"0.0000000000","unit":"USD per GB"},{"serviceId":"macie","region":"asia-pacific-(seoul)","attributes":{"usageType":"Data Transfer","feature":"Security"},"pricePerUnit":"0.2900000000","unit":"USD per GB"},{"serviceId":"macie","region":"asia-pacific-(seoul)","attributes":{"usageType":"Data Transfer","feature":"Security"},"pricePerUnit":"1.1500000000","unit":"USD per GB"},{"serviceId":"macie","region":"asia-pacific-(seoul)","attributes":{"usageType":"Data Transfer","feature":"Tier"},"pricePerUnit":"0.0000000000","unit":"USD per GB"},{"serviceId":"macie","region":"asia-pacific-(osaka)","attributes":{"feature":"Xtph"},"pricePerUnit":"0.0000000000","unit":"USD per unit"},{"serviceId":"macie","region":"asia-pacific-(osaka)","attributes":{"feature":"Tdym"},"pricePerUnit":"0.0000000000","unit":"USD per unit"},{"serviceId":"macie","region":"asia-pacific-(osaka)","attributes":{"feature":"Zvbyf"},"pricePerUnit":"1.2500000000","unit":"USD per unit"},{"serviceId":"macie","region":"asia-pacific-(osaka)","attributes":{"feature":"Mjek"},"pricePerUnit":"0.0000000000","unit":"USD per unit"},{"serviceId":"macie","region":"asia-pacific-(osaka)","attributes":{"usageType":"Data Transfer","feature":"Security"},"pricePerUnit":"0.0000000000","unit":"USD per unit"},{"serviceId":"macie","region":"asia-pacific-(osaka)","attributes":{"usageType":"Data Transfer","feature":"Security"},"pricePerUnit":"0.0000000000","unit":"USD per unit"},{"serviceId":"macie","region":"asia-pacific-(osaka)","attributes":{"feature":"Security"},"pricePerUnit":"0.0000000041","unit":"USD per unit"},{"serviceId":"macie","region":"asia-pacific-(osaka)","attributes":{"feature":"Security"},"pricePerUnit":"0.0000000000","unit":"USD per unit"},{"serviceId":"macie","region":"asia-pacific-(osaka)","attributes":{"usageType":"Data Transfer","feature":"Security"},"pricePerUnit":"0.0032880000","unit":"USD per unit"},{"serviceId":"macie","region":"asia-pacific-(osaka)","attributes":{"usageType":"Data Transfer","feature":"Security"},"pricePerUnit":"0.0032880000","unit":"USD per unit"},{"serviceId":"macie","region":"asia-pacific-(osaka)","attributes":{"usageType":"Data Transfer","feature":"Security"},"pricePerUnit":"0.6300000000","unit":"USD per GB"},{"serviceId":"macie","region":"asia-pacific-(osaka)","attributes":{"feature":"Security"},"pricePerUnit":"0.0000000000","unit":"USD per unit"},{"serviceId":"macie","region":"asia-pacific-(osaka)","attributes":{"usageType":"Data Transfer","feature":"Security"},"pricePerUnit":"0.0000000000","unit":"USD per GB"},{"serviceId":"macie","region":"asia-pacific-(osaka)","attributes":{"usageType":"Data Transfer","feature":"Security"},"pricePerUnit":"0.3100000000","unit":"USD per GB"},{"serviceId":"macie","region":"asia-pacific-(osaka)","attributes":{"usageType":"Data Transfer","feature":"Security"},"pricePerUnit":"1.2500000000","unit":"USD per GB"},{"serviceId":"macie","region":"asia-pacific-(osaka)","attributes":{"usageType":"Data Transfer","feature":"Tier"},"pricePerUnit":"0.0000000000","unit":"USD per GB"},{"serviceId":"macie","region":"asia-pacific-(mumbai)","attributes":{"feature":"Xtph"},"pricePerUnit":"0.0000000000","unit":"USD per unit"},{"serviceId":"macie","region":"asia-pacific-(mumbai)","attributes":{"feature":"Tdym"},"pricePerUnit":"0.0000000000","unit":"USD per unit"},{"serviceId":"macie","region":"asia-pacific-(mumbai)","attributes":{"feature":"Zvbyf"},"pricePerUnit":"1.2500000000","unit":"USD per unit"},{"serviceId":"macie","region":"asia-pacific-(mumbai)","attributes":{"feature":"Mjek"},"pricePerUnit":"0.0000000000","unit":"USD per unit"},{"serviceId":"macie","region":"asia-pacific-(mumbai)","attributes":{"usageType":"Data Transfer","feature":"Security"},"pricePerUnit":"0.0000000000","unit":"USD per unit"},{"serviceId":"macie","region":"asia-pacific-(mumbai)","attributes":{"usageType":"Data Transfer","feature":"Security"},"pricePerUnit":"0.0000000000","unit":"USD per unit"},{"serviceId":"macie","region":"asia-pacific-(mumbai)","attributes":{"feature":"Security"},"pricePerUnit":"0.0000000041","unit":"USD per unit"},{"serviceId":"macie","region":"asia-pacific-(mumbai)","attributes":{"feature":"Security"},"pricePerUnit":"0.0000000000","unit":"USD per unit"},{"serviceId":"macie","region":"asia-pacific-(mumbai)","attributes":{"usageType":"Data Transfer","feature":"Security"},"pricePerUnit":"0.0032880000","unit":"USD per unit"},{"serviceId":"macie","region":"asia-pacific-(mumbai)","attributes":{"usageType":"Data Transfer","feature":"Security"},"pricePerUnit":"0.0032880000","unit":"USD per unit"},{"serviceId":"macie","region":"asia-pacific-(mumbai)","attributes":{"usageType":"Data Transfer","feature":"Security"},"pricePerUnit":"0.6300000000","unit":"USD per GB"},{"serviceId":"macie","region":"asia-pacific-(mumbai)","attributes":{"feature":"Security"},"pricePerUnit":"0.0000000000","unit":"USD per unit"},{"serviceId":"macie","region":"asia-pacific-(mumbai)","attributes":{"usageType":"Data Transfer","feature":"Security"},"pricePerUnit":"0.0000000000","unit":"USD per GB"},{"serviceId":"macie","region":"asia-pacific-(mumbai)","attributes":{"usageType":"Data Transfer","feature":"Security"},"pricePerUnit":"0.3100000000","unit":"USD per GB"},{"serviceId":"macie","region":"asia-pacific-(mumbai)","attributes":{"usageType":"Data Transfer","feature":"Security"},"pricePerUnit":"1.2500000000","unit":"USD per GB"},{"serviceId":"macie","region":"asia-pacific-(mumbai)","attributes":{"usageType":"Data Transfer","feature":"Tier"},"pricePerUnit":"0.0000000000","unit":"USD per GB"},{"serviceId":"macie","region":"asia-pacific-(hong-kong)","attributes":{"feature":"Xtph"},"pricePerUnit":"0.0000000000","unit":"USD per unit"},{"serviceId":"macie","region":"asia-pacific-(hong-kong)","attributes":{"feature":"Tdym"},"pricePerUnit":"0.0000000000","unit":"USD per unit"},{"serviceId":"macie","region":"asia-pacific-(hong-kong)","attributes":{"feature":"Zvbyf"},"pricePerUnit":"1.3500000000","unit":"USD per unit"},{"serviceId":"macie","region":"asia-pacific-(hong-kong)","attributes":{"feature":"Mjek"},"pricePerUnit":"0.0000000000","unit":"USD per unit"},{"serviceId":"macie","region":"asia-pacific-(hong-kong)","attributes":{"usageType":"Data Transfer","feature":"Security"},"pricePerUnit":"0.0000000000","unit":"USD per unit"},{"serviceId":"macie","region":"asia-pacific-(hong-kong)","attributes":{"usageType":"Data Transfer","feature":"Security"},"pricePerUnit":"0.0000000000","unit":"USD per unit"},{"serviceId":"macie","region":"asia-pacific-(hong-kong)","attributes":{"feature":"Security"},"pricePerUnit":"0.0000000044","unit":"USD per unit"},{"serviceId":"macie","region":"asia-pacific-(hong-kong)","attributes":{"feature":"Security"},"pricePerUnit":"0.0000000000","unit":"USD per unit"},{"serviceId":"macie","region":"asia-pacific-(hong-kong)","attributes":{"usageType":"Data Transfer","feature":"Security"},"pricePerUnit":"0.0032880000","unit":"USD per unit"},{"serviceId":"macie","region":"asia-pacific-(hong-kong)","attributes":{"usageType":"Data Transfer","feature":"Security"},"pricePerUnit":"0.0032880000","unit":"USD per unit"},{"serviceId":"macie","region":"asia-pacific-(hong-kong)","attributes":{"usageType":"Data Transfer","feature":"Security"},"pricePerUnit":"0.6800000000","unit":"USD per GB"},{"serviceId":"macie","region":"asia-pacific-(hong-kong)","attributes":{"feature":"Security"},"pricePerUnit":"0.0000000000","unit":"USD per unit"},{"serviceId":"macie","region":"asia-pacific-(hong-kong)","attributes":{"usageType":"Data Transfer","feature":"Security"},"pricePerUnit":"0.0000000000","unit":"USD per GB"},{"serviceId":"macie","region":"asia-pacific-(hong-kong)","attributes":{"usageType":"Data Transfer","feature":"Security"},"pricePerUnit":"0.3400000000","unit":"USD per GB"},{"serviceId":"macie","region":"asia-pacific-(hong-kong)","attributes":{"usageType":"Data Transfer","feature":"Security"},"pricePerUnit":"1.3500000000","unit":"USD per GB"},{"serviceId":"macie","region":"asia-pacific-(hong-kong)","attributes":{"usageType":"Data Transfer","feature":"Tier"},"pricePerUnit":"0.0000000000","unit":"USD per GB"},{"serviceId":"macie","region":"africa-(cape-town)","attributes":{"feature":"Xtph"},"pricePerUnit":"0.0000000000","unit":"USD per unit"},{"serviceId":"macie","region":"africa-(cape-town)","attributes":{"feature":"Tdym"},"pricePerUnit":"0.0000000000","unit":"USD per unit"},{"serviceId":"macie","region":"africa-(cape-town)","attributes":{"feature":"Zvbyf"},"pricePerUnit":"1.2000000000","unit":"USD per unit"},{"serviceId":"macie","region":"africa-(cape-town)","attributes":{"feature":"Mjek"},"pricePerUnit":"0.0000000000","unit":"USD per unit"},{"serviceId":"macie","region":"africa-(cape-town)","attributes":{"usageType":"Data Transfer","feature":"Security"},"pricePerUnit":"0.0000000000","unit":"USD per unit"},{"serviceId":"macie","region":"africa-(cape-town)","attributes":{"usageType":"Data Transfer","feature":"Security"},"pricePerUnit":"0.0000000000","unit":"USD per unit"},{"serviceId":"macie","region":"africa-(cape-town)","attributes":{"feature":"Security"},"pricePerUnit":"0.0000000039","unit":"USD per unit"},{"serviceId":"macie","region":"africa-(cape-town)","attributes":{"feature":"Security"},"pricePerUnit":"0.0000000000","unit":"USD per unit"},{"serviceId":"macie","region":"africa-(cape-town)","attributes":{"usageType":"Data Transfer","feature":"Security"},"pricePerUnit":"0.0032880000","unit":"USD per unit"},{"serviceId":"macie","region":"africa-(cape-town)","attributes":{"usageType":"Data Transfer","feature":"Security"},"pricePerUnit":"0.0032880000","unit":"USD per unit"},{"serviceId":"macie","region":"africa-(cape-town)","attributes":{"usageType":"Data Transfer","feature":"Security"},"pricePerUnit":"0.6000000000","unit":"USD per GB"},{"serviceId":"macie","region":"africa-(cape-town)","attributes":{"feature":"Security"},"pricePerUnit":"0.0000000000","unit":"USD per unit"},{"serviceId":"macie","region":"africa-(cape-town)","attributes":{"usageType":"Data Transfer","feature":"Security"},"pricePerUnit":"0.0000000000","unit":"USD per GB"},{"serviceId":"macie","region":"africa-(cape-town)","attributes":{"usageType":"Data Transfer","feature":"Security"},"pricePerUnit":"0.3000000000","unit":"USD per GB"},{"serviceId":"macie","region":"africa-(cape-town)","attributes":{"usageType":"Data Transfer","feature":"Security"},"pricePerUnit":"1.2000000000","unit":"USD per GB"},{"serviceId":"macie","region":"africa-(cape-town)","attributes":{"usageType":"Data Transfer","feature":"Tier"},"pricePerUnit":"0.0000000000","unit":"USD per GB"}]